Workbook

Sheet Team
A1: Ordinis — Project Team
A3: SL | B3: Student ID | C3: Student Name | D3: Role
A4: 1 | B4: 23201023 | C4: Md. Nazmuz Saif | D4: Software Developer (Programmer)
A5: 2 | B5: 23201008 | C5: Fawjiya Fahima Eifa | D5: System Designer / Software Architect
A6: 3 | B6: 23201055 | C6: Montasim Kabir Mahin | D6: Project Manager
A7: 4 | B7: 23201029 | C7: Sadia Jahan Disha | D7: System Analyst / Business Analyst
A8: 5 | B8: 23201050 | C8: Md. Tahsin Rahman Khan | D8: Tester / Quality Assurance (QA) Engineer

Sheet Product Backlog
A1: Ordinis — Product Backlog
A2: Organization Operating System (OrgOS) — Multi-Tenant SaaS Platform
A4: Backlog ID | B4: Epic / Module | C4: User Story | D4: Priority | E4: Story Points | F4: Status | G4: Sprint Assigned | H4: Owner
A5: PB-01 | B5: Authentication & Onboarding | C5: As a Company Owner, I want to self-register my company and create my CEO account in one step, so that I can start using Ordinis without manual setup by an admin. | D5: High | E5: 5 | F5: Done | G5: Sprint 1 | H5: Md. Nazmuz Saif
A6: PB-02 | B6: Authentication & Onboarding | C6: As a User, I want to log in with my email and password, so that I can securely access my company's Ordinis dashboard. | D6: High | E6: 3 | F6: Done | G6: Sprint 1 | H6: Md. Nazmuz Saif
A7: PB-03 | B7: Authentication & Onboarding | C7: As a User, I want my login blocked if my company's subscription is suspended, so that access matches billing status. | D7: Medium | E7: 2 | F7: Done | G7: Sprint 1 | H7: Md. Nazmuz Saif
A8: PB-04 | B8: Organization Management | C8: As a CEO, I want to create and manage Departments for my company, so that I can structure my organization the way I need. | D8: High | E8: 3 | F8: Done | G8: Sprint 1 | H8: Md. Nazmuz Saif
A9: PB-05 | B9: Organization Management | C9: As a CEO, I want to create and manage Designations (job titles), so that employees can be labeled correctly without affecting their access rights. | D9: High | E9: 3 | F9: Done | G9: Sprint 1 | H9: Md. Nazmuz Saif
A10: PB-06 | B10: Organization Management | C10: As a CEO, I want to add Employees and assign each one a manager (reports-to), so that my real reporting hierarchy is reflected in the system. | D10: High | E10: 5 | F10: Done | G10: Sprint 1 | H10: Md. Nazmuz Saif
A11: PB-07 | B11: Organization Management | C11: As a Department Head, I want the system to resolve my full list of subordinates automatically, so that I can see my whole team regardless of hierarchy depth. | D11: Medium | E11: 5 | F11: Done | G11: Sprint 2 | H11: Md. Nazmuz Saif
A12: PB-08 | B12: RBAC (Roles & Permissions) | C12: As a CEO, I want to create custom Roles as bundles of Permissions, so that access rights are independent of job titles. | D12: High | E12: 5 | F12: Done | G12: Sprint 2 | H12: Montasim Kabir Mahin
A13: PB-09 | B13: RBAC (Roles & Permissions) | C13: As a CEO, I want to assign one or more Roles to any Employee, so that I can grant exactly the access that person needs. | D13: High | E13: 3 | F13: Done | G13: Sprint 2 | H13: Sadia Jahan Disha
A14: PB-10 | B14: RBAC (Roles & Permissions) | C14: As the System, I want every protected action to check a specific Permission codename, so that access control never depends on a hardcoded job-title check. | D14: High | E14: 5 | F14: Done | G14: Sprint 2 | H14: Fawjiya Fahima Eifa
A15: PB-11 | B15: RBAC (Roles & Permissions) | C15: As the System, I want the unfinished Sprint 2 RBAC work and the gaps left in PB-01, PB-07, and PB-10 closed, so that every protected action is really permission-checked and no company can reach another company's data. | D15: High | E15: 8 | F15: Done | G15: Sprint 3 | H15: Md. Nazmuz Saif
A16: PB-12 | B16: Approval Workflow | C16: As a CEO, I want to define a multi-step Approval Chain for leave requests, so that my company's actual approval process is enforced by the system. | D16: Medium | E16: 5 | F16: Done | G16: Sprint 3 | H16: Md. Nazmuz Saif
... A62: PB-58 | B62: Quality & Setup | C62: As a Team, I want the tests, documents and demo script to match the Sprint 6 system and one more full rehearsal, so that the final build is ready to present. | D62: High | E62: 5 | F62: To Do | G62: Sprint 6 | H62: Fawjiya Fahima Eifa

Sheet Sprint 1
A1: Ordinis — Sprint 1 Planning
A2: Sprint Duration: Sep 1 – Sep 9
A3: Sprint Goal: Stand up Company onboarding, authentication, and the core Organization structure (Department, Designation, Employee with hierarchy) so a company can self-register and build its org chart.
A5: Selected Stories for this Sprint
A6: Story ID | B6: User Story | C6: Owner | D6: Story Points | E6: Acceptance Criteria
A7: ST-101 | B7: As a Company Owner, I want to self-register my company and create my CEO account in one step, so that I can start using Ordinis without manual setup by an admin. | C7: Md. Nazmuz Saif | D7: 5 | E7: - Registration form creates Company, CompanySettings, CEO Designation, User, and Employee in one atomic transaction - A valid JWT is returned immediately - Registration fails cleanly (no partial records) if any step fails
A8: ST-102 | B8: As a User, I want to log in with my email and password, so that I can securely access my company's Ordinis dashboard. | C8: Md. Nazmuz Saif | D8: 3 | E8: - Valid credentials return an access token and a refresh token - Invalid credentials return a generic error (no enumeration) - Access token works on a protected endpoint; refresh token issues a new access token
A9: ST-103 | B9: As a User, I want my login blocked if my company's subscription is suspended, so that access matches billing status. | C9: Md. Nazmuz Saif | D9: 2 | E9: - Login from a suspended company returns a specific error and no token - An already-issued token from a since-suspended company is rejected on the next call
A10: ST-104 | B10: As a CEO, I want to create and manage Departments for my company, so that I can structure my organization the way I need. | C10: Md. Nazmuz Saif | D10: 3 | E10: - CRUD works for Departments, scoped strictly to the CEO's own company - Accessing another company's Department by ID returns 404
A11: ST-105 | B11: As a CEO, I want to create and manage Designations (job titles), so that employees can be labeled correctly without affecting their access rights. | C11: Md. Nazmuz Saif | D11: 3 | E11: - CRUD works for Designations, scoped to the CEO's own company - Creating/removing a Designation has no effect on any Employee's permissions
A12: ST-106 | B12: As a CEO, I want to add Employees and assign each one a manager (reports-to), so that my real reporting hierarchy is reflected in the system. | C12: Md. Nazmuz Saif | D12: 5 | E12: - Employee can be created with Department, Designation, and reports_to - Hierarchy supports any depth without code changes - An Employee cannot be set as their own manager
A14: Task Breakdown — one owner does the full story (Design → Database → Backend → Frontend → Self-Test)
A15: Story ID | B15: Category | C15: Task | D15: Owner | E15: Estimate (hrs) | F15: Status
A16: ST-101 | B16: Design | C16: Design Company + CompanySettings + CEO Designation data model and registration sequence | D16: Md. Nazmuz Saif | E16: 3 | F16: Done
A17: ST-101 | B17: Database | C17: Create and verify migrations for Company, CompanySettings, Designation, User, Employee | D17: Md. Nazmuz Saif | E17: 2 | F17: Done
A18: ST-101 | B18: Backend | C18: Build atomic CompanyRegisterSerializer (transaction-wrapped) + CompanyRegisterView | D18: Md. Nazmuz Saif | E18: 4 | F18: Done
A19: ST-101 | B19: Frontend | C19: Build Company Registration page (form, validation, API call) | D19: Md. Nazmuz Saif | E19: 3 | F19: Done
A20: ST-101 | B20: Self-Test | C20: Self-test registration with valid data and with a missing required field | D20: Md. Nazmuz Saif | E20: 1 | F20: Done
A21: ST-102 | B21: Design | C21: Design JWT token structure (claims: email, company_id) and refresh flow | D21: Md. Nazmuz Saif | E21: 2 | F21: Done
A22: ST-102 | B22: Backend | C22: Configure djangorestframework-simplejwt; build CustomTokenObtainPairSerializer; wire login/refresh endpoints | D22: Md. Nazmuz Saif | E22: 3 | F22: Done
A23: ST-102 | B23: Frontend | C23: Build Login page (form, error display, token storage) | D23: Md. Nazmuz Saif | E23: 3 | F23: Done
A24: ST-102 | B24: Self-Test | C24: Self-test login with valid and invalid credentials | D24: Md. Nazmuz Saif | E24: 1 | F24: Done
A25: ST-103 | B25: Backend | C25: Add is_active check to Company model and login serializer; build IsCompanyActive permission class | D25: Md. Nazmuz Saif | E25: 3 | F25: Done
A26: ST-103 | B26: Self-Test | C26: Self-test login attempt from a suspended-company account | D26: Md. Nazmuz Saif | E26: 1 | F26: Done
A27: ST-104 | B27: Design | C27: Design Department schema (company-scoped) | D27: Md. Nazmuz Saif | E27: 1 | F27: Done
... A41: ST-106 | B41: Self-Test | C41: Self-test hierarchy assignment across levels and the circular-reference block | D41: Md. Nazmuz Saif | E41: 1 | F41: Done
A43: Overall Testing — QA Pass (Md. Tahsin Rahman Khan)
A44: Story ID | B44: Test Case No. | C44: Test Case | D44: Owner | E44: Estimate (hrs) | F44: Result
A45: ST-101 | B45: TC-01 | C45: Register new company with valid data — expect Company, Settings, CEO Designation, User, Employee all created and a valid JWT returned | D45: Md. Tahsin Rahman Khan | E45: 1 | F45: to do
A46: ST-101 | B46: TC-02 | C46: Submit registration with a missing required field — expect a validation error and no partial records created | D46: Md. Tahsin Rahman Khan | E46: 1 | F46: to do
A47: ST-102 | B47: TC-03 | C47: Log in with valid credentials — expect access + refresh token returned | D47: Md. Tahsin Rahman Khan | E47: 1 | F47: to do
A48: ST-102 | B48: TC-04 | C48: Log in with invalid credentials — expect a generic error message, no token issued | D48: Md. Tahsin Rahman Khan | E48: 1 | F48: to do
A49: ST-103 | B49: TC-05 | C49: Attempt login as a user of a suspended company — expect a specific error and no token issued | D49: Md. Tahsin Rahman Khan | E49: 1 | F49: to do
A50: ST-104 | B50: TC-06 | C50: Create a Department — expect it visible only within the creating company's list | D50: Md. Tahsin Rahman Khan | E50: 1 | F50: to do
A51: ST-104 | B51: TC-07 | C51: Attempt to access another company's Department by ID — expect HTTP 404 | D51: Md. Tahsin Rahman Khan | E51: 1 | F51: to do
A52: ST-105 | B52: TC-08 | C52: Create, edit, and delete a Designation — expect changes scoped to own company only | D52: Md. Tahsin Rahman Khan | E52: 1 | F52: to do
A53: ST-106 | B53: TC-09 | C53: Assign an Employee's manager across a 3+ level hierarchy — expect the correct chain stored | D53: Md. Tahsin Rahman Khan | E53: 1 | F53: to do
A54: ST-106 | B54: TC-10 | C54: Attempt to set an Employee as their own manager — expect the request rejected | D54: Md. Tahsin Rahman Khan | E54: 1 | F54: to do
A56: Coordination Tasks (Montasim Kabir Mahin)
A57: Task | B57: Owner | C57: Estimate (hrs) | D57: Status
A58: Sprint 1 planning session — select stories from backlog, confirm scope | B58: Montasim Kabir Mahin | C58: 2 | D58: Done
A59: Daily coordination and progress tracking | B59: Montasim Kabir Mahin | C59: 3 | D59: Done
A60: Sprint 1 review and retrospective facilitation | B60: Montasim Kabir Mahin | C60: 2 | D60: Done
B62: Total Implementation Hours | E62: =SUM(E16:E41) -> 54
B63: Total QA Hours | E63: =SUM(E45:E54) -> 10
A64: Total Coordination Hours | C64: =SUM(C58:C60) -> 7

Sheet Sprint 2
A1: Ordinis — Sprint 2 Planning
A2: Sprint Duration: Sep 10 – Sep 23
A3: Sprint Goal: Deliver the RBAC engine (Roles as Permission bundles, independent of Designation) and recursive hierarchy resolution, completing the Core Engine's access-control foundation.
A5: Selected Stories for this Sprint
A6: Story ID | B6: User Story | C6: Owner | D6: Story Points | E6: Acceptance Criteria
A7: ST-107 | B7: As a Department Head, I want the system to resolve my full list of subordinates automatically, so that I can see my whole team regardless of hierarchy depth. | C7: Md. Nazmuz Saif | D7: 5 | E7: - Given an Employee, returns all direct and indirect subordinates - Given an Employee, returns the full chain of managers up to the top - Works for flat, 3-level, and 4+ level structures - Verified with real multi-level test data
A8: ST-108 | B8: As a CEO, I want to create custom Roles as bundles of Permissions, so that access rights are independent of job titles. | C8: Montasim Kabir Mahin | D8: 5 | E8: - CEO can create a Role with a name and a list of Permission codenames - A Role is scoped to the CEO's own company - Roles are retrievable independent of any Designation
A9: ST-109 | B9: As a CEO, I want to assign one or more Roles to any Employee, so that I can grant exactly the access that person needs. | C9: Sadia Jahan Disha | D9: 3 | E9: - CEO can assign a Role to any Employee in their company - An Employee can hold more than one Role at once - CEO can revoke a Role from an Employee
A10: ST-110 | B10: As the System, I want every protected action to check a specific Permission codename, so that access control never depends on a hardcoded job-title check. | C10: Fawjiya Fahima Eifa | D10: 5 | E10: - Employee.has_permission(codename) correctly reflects the Employee's assigned Roles' Permissions - A protected endpoint rejects the request if the acting Employee lacks the required permission - Verified: an Employee without a Role cannot perform a Role-gated action
A12: Carried Over from Sprint 1
A13: Story ID | B13: Category | C13: Task | D13: Owner | E13: Estimate (hrs) | F13: Status
A14: (none — Sprint 1 fully completed)
A16: Task Breakdown — one owner does the full story (Design → Database → Backend → Frontend → Self-Test)
A17: Story ID | B17: Category | C17: Task | D17: Owner | E17: Estimate (hrs) | F17: Status
A18: ST-107 | B18: Design | C18: Design recursive traversal approach for subordinate/manager resolution over reports_to | D18: Md. Nazmuz Saif | E18: 2 | F18: Done
A19: ST-107 | B19: Backend | C19: Implement get_all_subordinates(employee) and get_all_managers(employee) service functions | D19: Md. Nazmuz Saif | E19: 4 | F19: Done
A20: ST-107 | B20: Frontend | C20: Show subordinate list on the Employee detail view | D20: Md. Nazmuz Saif | E20: 2 | F20: Done
A21: ST-107 | B21: Self-Test | C21: Self-test recursive resolution against a 4-level test hierarchy | D21: Md. Nazmuz Saif | E21: 1 | F21: Done
A22: ST-108 | B22: Design | C22: Design Permission/Role/RolePermission schema, formalizing the Designation-vs-Role separation | D22: Montasim Kabir Mahin | E22: 2 | F22: Done
A23: ST-108 | B23: Database | C23: Create Permission and Role models and migrations | D23: Montasim Kabir Mahin | E23: 1 | F23: Done
A24: ST-108 | B24: Backend | C24: Build PermissionSerializer (read-only) and RoleSerializer/ViewSet | D24: Montasim Kabir Mahin | E24: 3 | F24: Done
A25: ST-108 | B25: Frontend | C25: Build Roles management page (create Role, select Permissions) | D25: Montasim Kabir Mahin | E25: 3 | F25: Done
A26: ST-108 | B26: Self-Test | C26: Self-test Role creation/retrieval and company-level scoping | D26: Montasim Kabir Mahin | E26: 1 | F26: Done
A27: ST-109 | B27: Design | C27: Design EmployeeRole schema (Employee <-> Role assignment) | D27: Sadia Jahan Disha | E27: 1 | F27: Done
A28: ST-109 | B28: Database | C28: Create EmployeeRole model and migration | D28: Sadia Jahan Disha | E28: 1 | F28: Done
A29: ST-109 | B29: Backend | C29: Build EmployeeRoleSerializer/ViewSet (assign/revoke) | D29: Sadia Jahan Disha | E29: 2 | F29: Done
... A35: ST-110 | B35: Self-Test | C35: Self-test that a permission-gated action is blocked without the permission and allowed with it | D35: Fawjiya Fahima Eifa | E35: 1 | F35: Pause
A37: Overall Testing — QA Pass (Md. Tahsin Rahman Khan)
A38: Story ID | B38: Test Case No. | C38: Test Case | D38: Owner | E38: Estimate (hrs) | F38: Result
A39: ST-107 | B39: TC-11 | C39: Get subordinates for a mid-level manager in a 4-level tree — expect the correct full descendant list | D39: Md. Tahsin Rahman Khan | E39: 1 | F39: to do
A40: ST-107 | B40: TC-12 | C40: Get the manager chain for a leaf-level Employee — expect the correct full ancestor chain | D40: Md. Tahsin Rahman Khan | E40: 1 | F40: to do
A41: ST-108 | B41: TC-13 | C41: Create a Role with a chosen Permission set — expect it retrievable with the correct Permissions | D41: Md. Tahsin Rahman Khan | E41: 1 | F41: to do
A42: ST-108 | B42: TC-14 | C42: Create a Role in Company A — expect it invisible to Company B | D42: Md. Tahsin Rahman Khan | E42: 1 | F42: to do
A43: ST-109 | B43: TC-15 | C43: Assign two Roles to one Employee — expect both retained simultaneously | D43: Md. Tahsin Rahman Khan | E43: 1 | F43: to do
A44: ST-109 | B44: TC-16 | C44: Revoke one Role from an Employee — expect the associated permission no longer granted | D44: Md. Tahsin Rahman Khan | E44: 1 | F44: to do
A45: ST-110 | B45: TC-17 | C45: Employee without the required permission attempts a protected action — expect the request blocked | D45: Md. Tahsin Rahman Khan | E45: 1 | F45: to do
A46: ST-110 | B46: TC-18 | C46: Employee with the correct permission performs the same action — expect it allowed | D46: Md. Tahsin Rahman Khan | E46: 1 | F46: to do
A48: Coordination Tasks (Montasim Kabir Mahin)
A49: Task | B49: Owner | C49: Estimate (hrs) | D49: Status
A50: Sprint 2 planning session — select stories from backlog, confirm scope | B50: Montasim Kabir Mahin | C50: 2 | D50: Done
A51: Daily coordination and progress tracking | B51: Montasim Kabir Mahin | C51: 3 | D51: Done
A52: Sprint 2 review and retrospective facilitation | B52: Montasim Kabir Mahin | C52: 2 | D52: Done
B54: Total Implementation Hours | E54: =SUM(E18:E35) -> 37
B55: Total QA Hours | E55: =SUM(E39:E46) -> 8
A56: Total Coordination Hours | C56: =SUM(C50:C52) -> 7

Sheet Sprint 3
A1: Ordinis — Sprint 3 Planning
A2: Sprint Duration: Sep 30 – Oct 7
A3: Sprint Goal: Close the Sprint 2 RBAC/tenant-safety gaps, then deliver the Approval Chain and approve/reject engine, the shared UI kit and app shell, Task create/submit, delegation, salary-data restriction, and check-in/out.
A5: Selected Stories for this Sprint
A6: Story ID | B6: User Story | D6: Owner | E6: Story Points | F6: Acceptance Criteria
A7: ST-111 | B7: PB-11: As the System, I want the unfinished Sprint 2 RBAC work and the gaps left in PB-01, PB-07, and PB-10 closed, so that every protected action is really permission-checked and no company can reach another company's data. | D7: Md. Nazmuz Saif | E7: 8 | F7: - HasPermission blocks a gated action when the Employee lacks the Permission - A user without a company can never be attached to another company (get_effective_company removed) - A new company's CEO gets a full-access CEO Role at registration - An Employee cannot be their own manager or create a reports_to cycle - Registration page, subordinate list, and Role assign/revoke on the Employee page exist - Employee removal ends the person's access; employee_code is unique per company; JWT refresh works
A8: ST-112 | B8: PB-12: As a CEO, I want to define a multi-step Approval Chain for leave requests, so that my company's actual approval process is enforced by the system. | D8: Md. Nazmuz Saif | E8: 5 | F8: - CEO can create a chain with ordered steps, each tied to a Role - Step order is unique inside a chain - Chain is scoped to own company (cross-company access returns 404) - Chain and steps can be edited and deleted
A9: ST-113 | B9: PB-13: As an Approver, I want to approve or reject a pending request with a comment, so that decisions and reasons are recorded. | D9: Md. Nazmuz Saif | E9: 3 | F9: - Only a holder of the current step's Role can act - Approve moves the request to the next step; the last approval completes it - Reject ends the request; a comment is stored with every action - The same step cannot be acted on twice
A10: ST-114 | B10: PB-16: As a User, I want every screen to use the same status badges, metric cards, empty states, and chart cards, so that the product looks consistent and is easy to learn. | D10: Md. Nazmuz Saif | E10: 3 | F10: - StatusPill, MetricCard, EmptyState, and ChartCard components exist - Status is shown by color and text, never color alone - All four follow the design system colors and 150–300ms animations - A showcase page at /dev/ui-kit displays every component
A11: ST-115 | B11: PB-20: As a User, I want a polished app shell (grouped sidebar, navbar, notification dropdown, company switcher, plan badge), so that the product feels professional and is easy to navigate. | D11: Md. Nazmuz Saif | E11: 5 | F11: - Sidebar has collapsible groups (Organization, Workflow, Tasks, Attendance, Finance) and highlights the active item - A menu item is hidden when the user lacks the Permission for it - Top bar shows the page title, search box, company name, notification bell, and user menu - The bell opens a dropdown with an empty state when there are no notifications - The plan badge next to the logo shows the plan name only when the server provides one (never hard-coded)
A12: ST-116 | B12: PB-14 + PB-15: As a Department Head, I want to create Tasks and assign them with a priority and deadline, and as an Employee I want to submit a Task only through valid status changes, so that work and progress are tracked correctly. | D12: Montasim Kabir Mahin | E12: 8 | F12: - Task has title, assignee, priority, deadline, and status (default Not Started) - Assignee must belong to the same company; assigned-by is set by the server - Only users with create_task can create, edit, or delete - Only valid status changes are accepted; an invalid one returns a clear error - Only the assignee can submit a Task
A13: ST-117 | B13: PB-17: As a Department Head, I want to delegate my approval authority to someone else for a date range, so that requests are not stuck when I'm on leave. | D13: Md. Tahsin Rahman Khan | E13: 3 | F13: - Delegation has delegate, start date, and end date - End date cannot be before start date; cannot delegate to self - Delegate must be in the same company
A14: ST-118 | B14: PB-18: As an Accountant, I want to define a Salary Structure per employee and keep salary and financial data restricted to users with finance permission, so that confidential pay data stays private regardless of hierarchy. | D14: Fawjiya Fahima Eifa | E14: 3 | F14: - A Salary Structure (base salary and allowances) can be defined per Employee - Salary Structure endpoints require the finance Permission - Access does not depend on the reporting hierarchy - Salary UI is hidden for users without the Permission
A15: ST-119 | B15: PB-19: As an Employee, I want to check in and check out once per day, so that my attendance is recorded accurately. | D15: Sadia Jahan Disha | E15: 3 | F15: - One check-in and one check-out per day, using the company's local time - A second check-in on the same day is rejected with a clear message - Check-out before check-in is rejected - Today's status is shown on the Attendance page
A17: Carried Over from Sprint 2
A18: Story ID | B18: Category | C18: Task | D18: Owner | E18: Estimate (hrs) | F18: Status
A19: ST-110 | B19: Design | C19: Design the HasPermission / PermissionRequiredMixin enforcement approach | D19: Md. Nazmuz Saif | E19: 2 | F19: Done (in ST-111)
A20: ST-110 | B20: Backend | C20: Implement HasPermission (real permission check) and apply it to gated actions | D20: Md. Nazmuz Saif | E20: 5 | F20: Done (in ST-111)
A21: ST-110 | B21: Frontend | C21: Hide/disable UI controls the current user lacks permission for | D21: Md. Nazmuz Saif | E21: 3 | F21: Done (in ST-111)
A22: ST-110 | B22: Self-Test | C22: Self-test that a gated action is blocked without the permission | D22: Md. Nazmuz Saif | E22: 1 | F22: Done (in ST-111)
A24: Task Breakdown — one owner does the full story (Design → Database → Backend → Frontend → Self-Test)
A25: Story ID | B25: Category | C25: Task | D25: Owner | E25: Estimate (hrs) | F25: Status
A26: ST-111 | B26: Design | C26: Design permission-enforcement flow, CEO Role bootstrap at registration, and tenant-safe company resolution | D26: Md. Nazmuz Saif | E26: 2 | F26: Done
A27: ST-111 | B27: Database | C27: Seed the full Permission set and verify all migrations on a fresh database | D27: Md. Nazmuz Saif | E27: 2 | F27: Done
A28: ST-111 | B28: Backend | C28: Fix HasPermission and IsCompanyActive; remove get_effective_company from mixins, views, serializers, and MeView | D28: Md. Nazmuz Saif | E28: 4 | F28: Done
A29: ST-111 | B29: Backend | C29: Create the CEO Role inside the atomic company registration; add PermissionRequiredMixin to RoleViewSet; move RBAC into the rbac app | D29: Md. Nazmuz Saif | E29: 4 | F29: Done
A30: ST-111 | B30: Backend | C30: Block self-manager and reports_to cycles on Employee create/update | D30: Md. Nazmuz Saif | E30: 2 | F30: Done
A31: ST-111 | B31: Frontend | C31: Build the Company Registration page (form, validation, API call, auto-login) | D31: Md. Nazmuz Saif | E31: 3 | F31: Done
A32: ST-111 | B32: Frontend | C32: Add subordinate list to Employee detail and Role assign/revoke to the Employee page; hide controls by permission | D32: Md. Nazmuz Saif | E32: 5 | F32: Done
A33: ST-111 | B33: Self-Test | C33: Self-test 403 without permission, 200 with it, cross-company access, cycle block, and fresh-DB registration | D33: Md. Nazmuz Saif | E33: 2 | F33: Done
A34: ST-112 | B34: Design | C34: Design ApprovalChain and ApprovalStep schema (ordered steps, approver Role) | D34: Md. Nazmuz Saif | E34: 2 | F34: Done
A35: ST-112 | B35: Database | C35: Create the approvals app models and migrations; seed the chain-management Permission | D35: Md. Nazmuz Saif | E35: 2 | F35: Done
A36: ST-112 | B36: Backend | C36: Build ApprovalChain/ApprovalStep serializers and ViewSets (company-scoped, step order unique) | D36: Md. Nazmuz Saif | E36: 4 | F36: Done
A37: ST-112 | B37: Frontend | C37: Build the Approval Chains page (create chain, add ordered steps with Role, edit, delete) | D37: Md. Nazmuz Saif | E37: 4 | F37: Done
... A72: ST-119 | B72: Self-Test | C72: Self-test check-in, duplicate check-in, and check-out before check-in | D72: Sadia Jahan Disha | E72: 1 | F72: Done
A74: Cross-Test Assignment — every story is tested by a member who did not write it
A75: Story ID | C75: Story | D75: Code Owner | F75: Selenium Tester
A76: ST-111 | C76: Sprint 2 RBAC carry-over | D76: Md. Nazmuz Saif | F76: Montasim Kabir Mahin
A77: ST-112 | C77: Approval Chain | D77: Md. Nazmuz Saif | F77: Sadia Jahan Disha
A78: ST-113 | C78: Approve / reject | D78: Md. Nazmuz Saif | F78: Fawjiya Fahima Eifa
A79: ST-114 | C79: UI component kit | D79: Md. Nazmuz Saif | F79: Md. Tahsin Rahman Khan
A80: ST-115 | C80: App shell | D80: Md. Nazmuz Saif | F80: Sadia Jahan Disha
A81: ST-116 | C81: Task create, assign, submit | D81: Montasim Kabir Mahin | F81: Md. Nazmuz Saif
A82: ST-117 | C82: Approval delegation | D82: Md. Tahsin Rahman Khan | F82: Montasim Kabir Mahin
A83: ST-118 | C83: Salary data restriction | D83: Fawjiya Fahima Eifa | F83: Md. Tahsin Rahman Khan
A84: ST-119 | C84: Check-in / check-out | D84: Sadia Jahan Disha | F84: Fawjiya Fahima Eifa
A86: Overall Testing — Selenium Cross-Review QA Pass (each tester tests another member's story)
A87: Story ID | B87: Test Case No. | C87: Test Case | D87: Tester | E87: Estimate (hrs) | F87: Result
A88: ST-111 | B88: TC-19 | C88: [Selenium] Log in as an Employee without the manage_departments Permission and try to add a Department — expect an error message and no record created | D88: Montasim Kabir Mahin | E88: 1.5 | F88: Passed
A89: ST-111 | B89: TC-20 | C89: [Selenium] Log in as a CEO right after registration and add a Department — expect success (CEO Role assigned automatically) | D89: Montasim Kabir Mahin | E89: 1.5 | F89: Passed
A90: ST-111 | B90: TC-21 | C90: [Selenium] Register a new company from the registration page — expect a redirect to the dashboard as CEO of that company only | D90: Montasim Kabir Mahin | E90: 1.5 | F90: Passed
A91: ST-111 | B91: TC-22 | C91: [Selenium] Try to set an Employee as their own manager or create a reports_to cycle — expect the request blocked with a message | D91: Montasim Kabir Mahin | E91: 1.5 | F91: Passed
A92: ST-111 | B92: TC-23 | C92: [Selenium] Open an Employee detail page — expect the subordinate list; assign then revoke a Role — expect the page to update | D92: Montasim Kabir Mahin | E92: 1.5 | F92: Passed
A93: ST-112 | B93: TC-24 | C93: [Selenium] Create an Approval Chain with three ordered steps — expect the steps saved in order | D93: Sadia Jahan Disha | E93: 1.5 | F93: Passed
A94: ST-112 | B94: TC-25 | C94: [Selenium] Add a step with a duplicate order or no Role — expect a validation error | D94: Sadia Jahan Disha | E94: 1.5 | F94: Passed
A95: ST-112 | B95: TC-26 | C95: [Selenium] Log in as Company B and open Company A's chain by ID — expect HTTP 404 | D95: Sadia Jahan Disha | E95: 1.5 | F95: Passed
A96: ST-113 | B96: TC-27 | C96: [Selenium] Approve as the holder of the current step's Role — expect the request to move to the next step | D96: Fawjiya Fahima Eifa | E96: 1.5 | F96: Passed
A97: ST-113 | B97: TC-28 | C97: [Selenium] Reject with a comment — expect the request to end and the comment to be shown in the history | D97: Fawjiya Fahima Eifa | E97: 1.5 | F97: Passed
A98: ST-113 | B98: TC-29 | C98: [Selenium] Try to approve without the step's Role, or act on the same step twice — expect the action blocked | D98: Fawjiya Fahima Eifa | E98: 1.5 | F98: Passed
A99: ST-114 | B99: TC-30 | C99: [Selenium] Open /dev/ui-kit — expect Success, Warning, and Failed status pills, each with color and text | D99: Md. Tahsin Rahman Khan | E99: 1.5 | F99: Passed
... A119: ST-119 | B119: TC-50 | C119: [Selenium] Log in as a new Employee and click Check Out before Check In — expect the request blocked | D119: Fawjiya Fahima Eifa | E119: 1.5 | F119: Passed
A121: Coordination Tasks (Montasim Kabir Mahin)
A122: Task | B122: Owner | C122: Estimate (hrs) | D122: Status
A123: Sprint 3 planning session — select stories from backlog, confirm scope | B123: Montasim Kabir Mahin | C123: 2 | D123: Done
A124: Daily coordination and progress tracking | B124: Montasim Kabir Mahin | C124: 3 | D124: Done
A125: Cross-test hand-off tracking — confirm each story is tested by a non-owner | B125: Montasim Kabir Mahin | C125: 1 | D125: Done
A126: Sprint 3 review and retrospective facilitation | B126: Montasim Kabir Mahin | C126: 2 | D126: Done
B128: Total Implementation Hours | E128: =SUM(E26:E72) -> 104
B129: Total QA Hours | E129: =SUM(E88:E119) -> 48
A130: Total Coordination Hours | C130: =SUM(C123:C126) -> 8

Sheet Sprint 4
A1: Ordinis — Sprint 4 Planning
A2: Sprint Duration: Oct 7 – Oct 14
A3: Sprint Goal: Finish the Sprint 3 Salary Structure carry-over, then deliver paginated and documented APIs, Role dashboards, the Break-Glass support process and platform admin panel, the Task Kanban board with daily progress, the Action Inbox, Payslip generation, and leave application with balance check.
A5: Selected Stories for this Sprint
A6: Story ID | B6: User Story | D6: Owner | E6: Story Points | F6: Acceptance Criteria
A7: ST-120 | B7: PB-40: As an Accountant, I want the unfinished Sprint 3 Salary Structure work (database, API, self-test and the Edit/Delete screen) completed, so that confidential pay data can be defined, edited and deleted per employee and stays restricted to users with the finance Permission. | D7: Md. Nazmuz Saif | E7: 3 | F7: - A Salary Structure (base salary and allowances) can be created, edited and deleted per Employee - Every Salary Structure endpoint requires the finance Permission, whatever the reporting hierarchy - One structure per Employee; a negative base salary or allowance is rejected - The page is hidden for users without the Permission; Edit and Delete work on the page - TC-46 (create and edit), which Failed in Sprint 3, passes when run again
A8: ST-121 | B8: PB-21: As a Developer, I want all list endpoints paginated and the project set up with requirements, environment example, and README, so that the system scales and can be installed by anyone. | D8: Md. Nazmuz Saif | E8: 3 | F8: - Every list endpoint returns pages (page size 20) and the frontend lists still work - requirements.txt installs everything on a clean machine - .env.example lists every environment variable with no secrets - README explains install, migrate, run backend and frontend, and run the tests
A9: ST-122 | B9: PB-22: As a User, I want a dashboard made for my Role (CEO, Manager, HR, Accountant, Employee), so that I see only what matters to my work. | D9: Md. Nazmuz Saif | E9: 8 | F9: - After login the user lands on a dashboard; the Dashboard menu item is no longer "Soon" - What a dashboard shows is decided by the user's Permissions, not by the Designation name - Each dashboard has a row of MetricCards with real numbers from the API and at least one chart - A user never sees numbers they lack the Permission for (for example salary data) - Loading and empty states use the UI kit
A10: ST-123 | B10: PB-23: As the Platform Owner, I want a Break-Glass access process for support, so that I can help a client without having default access to their data. | D10: Md. Nazmuz Saif | E10: 5 | F10: - A Platform Admin sends a Support Access Request with a reason - The company CEO sees the request and approves or denies it - Approval gives time-limited access that expires on its own - Without an approved, unexpired request the Platform Admin cannot read the company's data - Every use is recorded in an Impersonation Log the company can read
A11: ST-124 | B11: PB-24: As the Platform Owner, I want an admin panel for companies, support tickets, and Break-Glass requests, so that I can operate the platform without seeing client data by default. | D11: Md. Nazmuz Saif | E11: 5 | F11: - The panel lists companies, support tickets, and Break-Glass requests - A company can be suspended and activated; users of a suspended company cannot log in - The panel shows no employee, task, or salary data - Only Platform Admin accounts can open it; everybody else is blocked and does not see the menu item
A12: ST-125 | B12: PB-25 + PB-26: As a Department Head, I want to see Tasks on a Kanban board (To Do, In Progress, Review, Done), and as an Employee I want to log daily progress on a multi-day task, so that my manager can see progress at a glance without me uploading code or files. | D12: Montasim Kabir Mahin | E12: 8 | F12: - The Kanban board shows the four columns with a count on each and a card per Task (title, priority, assignee, deadline) - A card can only move along the allowed status path; a wrong move is rejected with a clear message - The assignee can add a daily progress entry (text, progress percent, optional blocker, optional external link); no file or code upload - The entries show as a timeline on the Task; only the assignee can add them; another company's Task is not reachable
A13: ST-126 | B13: PB-27: As a User, I want a personalized Action Inbox combining my pending tasks, approvals, and notifications, so that I know what needs my attention in one place. | D13: Md. Tahsin Rahman Khan | E13: 5 | F13: - One list shows my open Tasks, the approvals waiting for me, and my unread notifications - A Notification is created when a Task is assigned to me or an approval reaches me - Other users' and other companies' items never appear; each item opens its page - Marking a notification read removes it from the unread list; an empty inbox shows an empty state
A14: ST-127 | B14: PB-28: As an Accountant, I want to generate a Payslip for a given month without creating duplicates, so that payroll runs stay accurate. | D14: Sadia Jahan Disha | E14: 5 | F14: - A Payslip for an Employee and month shows gross, deductions, and net, calculated from the Salary Structure - A second Payslip for the same Employee and month is rejected (also enforced in the database) - Generating needs the finance Permission, whatever the reporting hierarchy - An Employee without a Salary Structure gets a clear message; an Employee can open only their own Payslip
A15: ST-128 | B15: PB-29: As an Employee, I want to apply for leave and have my balance validated automatically, so that I can't accidentally over-request leave. | D15: Fawjiya Fahima Eifa | E15: 5 | F15: - A company can define Leave Types with days allowed per year - An Employee can apply with leave type, start date, end date, and reason; the request starts as Pending - A request above the remaining balance is rejected with a message that shows the remaining days - An end date before the start date is rejected; an Employee sees only their own requests
A17: Carried Over from Sprint 3
A18: Story ID | B18: Category | C18: Task | D18: Owner | E18: Estimate (hrs) | F18: Status
A19: ST-118 | B19: Database | C19: Create the payroll app SalaryStructure model and migration; seed the finance Permission | D19: Fawjiya Fahima Eifa | E19: 1 | F19: Done (in ST-120)
A20: ST-118 | B20: Backend | C20: Build SalaryStructure serializer and ViewSet gated by the finance Permission | D20: Fawjiya Fahima Eifa | E20: 2 | F20: Done (in ST-120)
A21: ST-118 | B21: Self-Test | C21: Self-test access with and without the finance Permission | D21: Fawjiya Fahima Eifa | E21: 1 | F21: Done (in ST-120)
A22: ST-118 | B22: Selenium | C22: TC-46 (create and edit a Salary Structure) Failed in Sprint 3 and is run again as TC-51 | D22: Md. Tahsin Rahman Khan | E22: 1.5 | F22: Done (in ST-120)
A24: Task Breakdown — one owner does the full story (Design → Database → Backend → Frontend → Self-Test)
A25: Story ID | B25: Category | C25: Task | D25: Owner | E25: Estimate (hrs) | F25: Status
A26: ST-120 | B26: Database | C26: Create the payroll app SalaryStructure model and migration; seed the finance Permission | D26: Md. Nazmuz Saif | E26: 1 | F26: Done
A27: ST-120 | B27: Backend | C27: Build SalaryStructure serializer and ViewSet gated by the finance Permission (no hierarchy rule, one structure per Employee) | D27: Md. Nazmuz Saif | E27: 2 | F27: Done
A28: ST-120 | B28: Frontend | C28: Fix the Salary Structures page: Edit and Delete work, statuses show correctly, UI kit components are used, page is hidden without the Permission | D28: Md. Nazmuz Saif | E28: 2 | F28: Done
A29: ST-120 | B29: Self-Test | C29: Self-test create, edit, delete, access with and without the finance Permission, and the manager-above-Accountant case | D29: Md. Nazmuz Saif | E29: 1 | F29: Done
A30: ST-121 | B30: Design | C30: Design the pagination format and what changes in the frontend lists | D30: Md. Nazmuz Saif | E30: 1 | F30: Done
A31: ST-121 | B31: Backend | C31: Wire pagination into every list endpoint and keep the standard response format | D31: Md. Nazmuz Saif | E31: 2 | F31: Done
A32: ST-121 | B32: Backend | C32: Write requirements.txt, .env.example, and the README (install, migrate, run, test) | D32: Md. Nazmuz Saif | E32: 2 | F32: Done
A33: ST-121 | B33: Frontend | C33: Update every frontend list service and page to read paged results and add page controls | D33: Md. Nazmuz Saif | E33: 3 | F33: Done
A34: ST-121 | B34: Self-Test | C34: Self-test a long list on two pages and a clean install from the README | D34: Md. Nazmuz Saif | E34: 1 | F34: Done
A35: ST-122 | B35: Design | C35: Design the five Role dashboards (which MetricCards and charts, which Permission each needs) | D35: Md. Nazmuz Saif | E35: 2 | F35: Done
A36: ST-122 | B36: Backend | C36: Build the dashboard summary endpoint(s) that return only what the user's Permissions allow | D36: Md. Nazmuz Saif | E36: 3 | F36: Done
A37: ST-122 | B37: Frontend | C37: Build the CEO, Manager, HR, Accountant, and Employee dashboards with MetricCards and charts (violet palette) | D37: Md. Nazmuz Saif | E37: 8 | F37: Done
... A68: ST-128 | B68: Self-Test | C68: Self-test an in-balance request, an over-balance request, and reversed dates | D68: Fawjiya Fahima Eifa | E68: 1 | F68: Done
A70: Cross-Test Assignment — every story is tested by a member who did not write its code
A71: Story ID | C71: Story | D71: Code Owner | F71: Selenium Tester
A72: ST-120 | C72: Salary Structure carry-over | D72: Md. Nazmuz Saif | F72: Md. Tahsin Rahman Khan
A73: ST-121 | C73: Pagination and project setup | D73: Md. Nazmuz Saif | F73: Md. Tahsin Rahman Khan
A74: ST-122 | C74: Role dashboards | D74: Md. Nazmuz Saif | F74: Md. Tahsin Rahman Khan
A75: ST-123 | C75: Break-Glass support access | D75: Md. Nazmuz Saif | F75: Md. Tahsin Rahman Khan
A76: ST-124 | C76: Platform admin panel | D76: Md. Nazmuz Saif | F76: Md. Tahsin Rahman Khan
A77: ST-125 | C77: Kanban board and daily progress | D77: Montasim Kabir Mahin | F77: Md. Nazmuz Saif
A78: ST-126 | C78: Action Inbox | D78: Md. Tahsin Rahman Khan | F78: Montasim Kabir Mahin
A79: ST-127 | C79: Payslip generation | D79: Sadia Jahan Disha | F79: Fawjiya Fahima Eifa
A80: ST-128 | C80: Leave application with balance check | D80: Fawjiya Fahima Eifa | F80: Sadia Jahan Disha
A82: Overall Testing — Selenium Cross-Review QA Pass (each tester tests another member's code)
A83: Story ID | B83: Test Case No. | C83: Test Case | D83: Tester | E83: Estimate (hrs) | F83: Result
A84: ST-120 | B84: TC-51 | C84: [Selenium] Log in with the finance Permission, create a Salary Structure and edit it — expect the saved values in the list (TC-46 run again) | D84: Md. Tahsin Rahman Khan | E84: 1.5 | F84: Passed
A85: ST-120 | B85: TC-52 | C85: [Selenium] Delete a Salary Structure — expect it gone from the list; log in without the Permission — expect no menu item | D85: Md. Tahsin Rahman Khan | E85: 1.5 | F85: Passed
A86: ST-121 | B86: TC-53 | C86: [Selenium] Open a list with more than one page — expect page controls and that the next page loads | D86: Md. Tahsin Rahman Khan | E86: 1.5 | F86: Passed
A87: ST-122 | B87: TC-54 | C87: [Selenium] Log in as a CEO — expect the dashboard with MetricCards showing numbers and a chart | D87: Md. Tahsin Rahman Khan | E87: 1.5 | F87: Passed
A88: ST-122 | B88: TC-55 | C88: [Selenium] Log in as an Employee — expect only Employee metrics and no salary or company-wide numbers | D88: Md. Tahsin Rahman Khan | E88: 1.5 | F88: Passed
A89: ST-122 | B89: TC-56 | C89: [Selenium] Log in as an Accountant — expect finance metrics and no Task management numbers | D89: Md. Tahsin Rahman Khan | E89: 1.5 | F89: Passed
A90: ST-123 | B90: TC-57 | C90: [Selenium] As a Platform Admin send a Support Access Request with a reason — expect it Pending; as the CEO see it in the list | D90: Md. Tahsin Rahman Khan | E90: 1.5 | F90: Passed
A91: ST-123 | B91: TC-58 | C91: [Selenium] As the CEO approve the request — expect an expiry time and a log entry; without an approved request — expect access blocked | D91: Md. Tahsin Rahman Khan | E91: 1.5 | F91: Passed
A92: ST-124 | B92: TC-59 | C92: [Selenium] As a Platform Admin open the panel and suspend a company — expect its users cannot log in; activate it — expect they can | D92: Md. Tahsin Rahman Khan | E92: 1.5 | F92: Passed
A93: ST-124 | B93: TC-60 | C93: [Selenium] As a CEO open the admin panel address — expect access blocked and no menu item | D93: Md. Tahsin Rahman Khan | E93: 1.5 | F93: Passed
A94: ST-125 | B94: TC-61 | C94: [Selenium] Open the Kanban board — expect the four columns with counts and Task cards | D94: Md. Nazmuz Saif | E94: 1.5 | F94: Passed
A95: ST-125 | B95: TC-62 | C95: [Selenium] As the assignee add a daily progress entry — expect it on the Task timeline | D95: Md. Nazmuz Saif | E95: 1.5 | F95: Passed
... A103: ST-128 | B103: TC-70 | C103: [Selenium] Enter an end date before the start date — expect a validation message | D103: Sadia Jahan Disha | E103: 1.5 | F103: Passed
A105: Coordination Tasks (Montasim Kabir Mahin)
A106: Task | B106: Owner | C106: Estimate (hrs) | D106: Status
A107: Sprint 4 planning session — select stories from backlog, confirm scope | B107: Montasim Kabir Mahin | C107: 2 | D107: Done
A108: Daily coordination and progress tracking | B108: Montasim Kabir Mahin | C108: 3 | D108: Done
A109: Cross-test hand-off tracking — confirm each story is tested by a non-owner | B109: Montasim Kabir Mahin | C109: 1 | D109: Done
A110: Sprint 4 review and retrospective facilitation | B110: Montasim Kabir Mahin | C110: 2 | D110: Done
B112: Total Implementation Hours | E112: =SUM(E26:E68) -> 104
B113: Total QA Hours | E113: =SUM(E84:E103) -> 30
A114: Total Coordination Hours | C114: =SUM(C107:C110) -> 8

Sheet Sprint 5
A1: Ordinis — Sprint 5 Planning
A2: Sprint Duration: Oct 14 – Oct 21
A3: Sprint Goal: Finish the product. Connect leave to the Approval Chain, add the Audit Log, Analytics, Billing and the attendance calendar, then fill the system with demo data, build the regression suite, update every document and rehearse the full demo.
A5: Selected Stories for this Sprint
A6: Story ID | B6: User Story | D6: Owner | E6: Story Points | F6: Acceptance Criteria
A7: ST-129 | B7: As an Employee, I want my leave request to follow my company's Approval Chain, and approvers to approve or reject it, so that leave is decided by the right people in the right order. (PB-30) | D7: Md. Nazmuz Saif | E7: 5 | F7: - Applying for leave starts the company's leave Approval Chain; the request stays Pending until its last step is approved - Each step's approvers (role holders and their active delegates) see the request in Pending Approvals and in their Action Inbox; the applicant never decides their own request - Approving the last step makes the leave Approved; a rejection with a comment makes it Rejected; both send a Notification to the applicant and a Rejected leave gives its days back - If the company has no leave chain, or a step has no approver, the request goes to the CEO instead of getting stuck - A decided request cannot be decided again; another company's request is not reachable
A8: ST-130 | B8: As a Presenter, I want a command that fills the system with realistic demo data, so that every screen looks real during the demo. (PB-31) | D8: Md. Nazmuz Saif | E8: 3 | F8: - One command creates a demo company with a CEO, departments, designations, a multi-level hierarchy, Roles, and a sample user for every dashboard (CEO, Manager, HR, Accountant, Employee) - It adds Tasks in all four Kanban columns with progress entries, a month of attendance, leave types and leave requests in every status, salary structures and payslips, an approval chain with requests waiting, and notifications - Running it twice never duplicates data; a --reset option removes only the demo company; it refuses to run with production settings - Every screen shows real-looking data after the command
A9: ST-131 | B9: As a Developer, I want a Selenium regression suite and backend tests, so that changes cannot silently break working features. (PB-32) | D9: Md. Nazmuz Saif | E9: 5 | F9: - One command runs every backend test and one command runs every Selenium test case (TC-01 onward) against the demo company, printing pass or fail for each test case - Every API endpoint has tests for: login required, the Permission check, and another company's data returning 404 - A shared Selenium helper (login that works after the dashboard redirect, one place for the frontend address, test users) replaces the copies in each test file - The README explains how to run both suites
A10: ST-132 | B10: As a Reviewer, I want the SRS, SDS, and structure documents to match the delivered system, so that the documents are trustworthy. (PB-33) | D10: Md. Nazmuz Saif | E10: 3 | F10: - The SRS, SDS, project structure, ER diagram, design system and the other project documents describe only what the delivered system really has - The SDS data dictionary and API table match the code (models, fields, endpoints); anything not built is marked as future work - The SRS traceability table marks every requirement Done, Partly or Not built, with the story that delivered it - The documents are checked against the latest code by someone other than the author
A11: ST-133 | B11: As a Team, I want a full demo rehearsal with a bug-fix buffer, so that the final presentation runs smoothly. (PB-34) | D11: Md. Nazmuz Saif | E11: 5 | F11: - A written demo script walks every role through the main features in order, in about 15 minutes - The script is rehearsed end to end twice on a clean install with demo data; every slip is logged and then fixed or listed as known - At least 6 hours stay free as a bug-fix buffer, and no new feature is added after the first rehearsal - The final build passes both test suites, npm run lint and npm run build
A12: ST-134 | B12: As a CEO, I want an Analytics page with attendance and task-completion charts, so that I can see my company's health. (PB-35) | D12: Montasim Kabir Mahin | E12: 5 | F12: - The CEO opens an Analytics page with a row of MetricCards (attendance rate, task completion rate, overdue tasks, average team workload) - A line chart shows the attendance rate over the last 6 months and a grouped bar chart shows completed and pending Tasks by department - All numbers come from the real attendance and task data of the user's own company; a month without data shows 0, not an error - Users without the analytics Permission never see the menu item or the numbers; the page has loading and empty states
A13: ST-135 | B13: As a CEO, I want every sensitive action logged in an append-only Audit Log, and an Audit Log page with module filter and export, so that I have a tamper-proof history of who did what and when. (PB-36 + PB-37) | D13: Md. Tahsin Rahman Khan | E13: 8 | F13: - Every create, update and delete through the API, plus Break-Glass reads, payslip generation and leave decisions, writes an Audit Log row with actor, action, module, object, company and time - The Audit Log is append-only: no edit or delete endpoint exists, and the model refuses update and delete - The CEO sees only the log of their own company; a user without the Permission is blocked - The Audit Log page shows User, Action, Module, Date & Time and a Status pill, with a Module filter, an Export button and paging; it has no edit or delete action
A14: ST-136 | B14: As a CEO, I want a Billing page showing my plan, employee limit, and invoices, so that I can manage my subscription. (PB-38) | D14: Sadia Jahan Disha | E14: 3 | F14: - The Billing page shows the company's plan (name, price, employee limit), the current employee count with a usage bar, and the invoice list - Plans are seeded (Basic 10 employees, Professional 50, Enterprise unlimited) and a new company starts on Basic - Adding an Employee beyond the plan's limit is refused with a clear "upgrade your plan" message - Only users with the billing Permission see the page and its data; another company's invoices are not reachable
A15: ST-137 | B15: As an Employee, I want a monthly attendance calendar with summary cards, so that I can see my attendance history at a glance. (PB-39) | D15: Fawjiya Fahima Eifa | E15: 3 | F15: - A month calendar shows a colored dot per day (Present, Absent, On Leave) with previous and next month buttons - Summary cards show Present, Absent and On Leave days and the attendance rate of the month - Days of Approved leave show as On Leave; weekends and future days show no status - An employee sees only their own calendar
A17: Carried Over from Sprint 4
A18: Story ID | B18: Category | C18: Task | D18: Owner | E18: Estimate (hrs) | F18: Status
A19: — | B19: — | C19: Nothing was carried over: every Sprint 4 story is Done and every test case Passed | D19: — | E19: 0 | F19: Done
A21: Task Breakdown (Implementation)
A22: Story ID | B22: Category | C22: Task | D22: Owner | E22: Estimate (hrs) | F22: Status
A23: ST-129 | B23: Design | C23: Design how a leave request starts an Approval Instance of the leave chain, what approve and reject do, and the CEO fallback when no chain or approver exists | D23: Md. Nazmuz Saif | E23: 1 | F23: Done
A24: ST-129 | B24: Backend | C24: Connect apply_leave to start_approval; on the last approval set the leave Approved, on rejection set it Rejected and give the days back; block the applicant from deciding their own leave | D24: Md. Nazmuz Saif | E24: 5 | F24: Done
A25: ST-129 | B25: Backend | C25: Notify the applicant when the leave is decided and show the leave in the approvers' Pending Approvals and Action Inbox; add the CEO fallback | D25: Md. Nazmuz Saif | E25: 2 | F25: Done
A26: ST-129 | B26: Frontend | C26: Show the approval progress (current step, who decided, comment) on the My Leave page and the leave details on Pending Approvals | D26: Md. Nazmuz Saif | E26: 3 | F26: Done
A27: ST-129 | B27: Self-Test | C27: Self-test a one-step and a two-step chain, a rejection with a comment, no chain configured, the applicant's own request, and another company | D27: Md. Nazmuz Saif | E27: 2 | F27: Done
A28: ST-130 | B28: Design | C28: Design the demo story: the company, one account per role, and the data each screen needs | D28: Md. Nazmuz Saif | E28: 1 | F28: Done
A29: ST-130 | B29: Backend | C29: Write the seed_demo_data command: safe to run twice, a --reset for the demo company only, refuses production settings | D29: Md. Nazmuz Saif | E29: 5 | F29: Done
A30: ST-130 | B30: Self-Test | C30: Run the command on an empty database and twice in a row, log in as every demo role and check each screen has data | D30: Md. Nazmuz Saif | E30: 2 | F30: Done
A31: ST-131 | B31: Design | C31: Decide what the regression suite covers and how a Selenium run starts from known demo data | D31: Md. Nazmuz Saif | E31: 1 | F31: Done
A32: ST-131 | B32: Backend | C32: Add the missing backend tests so every endpoint is tested for login required, the Permission check, and another company's data returning 404 | D32: Md. Nazmuz Saif | E32: 6 | F32: Done
A33: ST-131 | B33: Backend | C33: Build the shared Selenium helper (login after the dashboard redirect, frontend address, test users) and one command that runs every Selenium test case | D33: Md. Nazmuz Saif | E33: 3 | F33: Done
A34: ST-131 | B34: Self-Test | C34: Run both suites from a clean checkout and fix what breaks; write the README steps | D34: Md. Nazmuz Saif | E34: 3 | F34: Done
... A61: ST-137 | B61: Self-Test | C61: Self-test months with no data, a month with approved leave, and that another employee's days never show | D61: Fawjiya Fahima Eifa | E61: 1 | F61: Done
A63: Cross-Test Assignment (every story is tested by someone other than its owner)
A64: Story ID | C64: Story | D64: Code Owner | F64: Selenium Tester
A65: ST-129 | C65: Leave follows the Approval Chain | D65: Md. Nazmuz Saif | F65: Md. Tahsin Rahman Khan
A66: ST-130 | C66: Demo data command | D66: Md. Nazmuz Saif | F66: Md. Tahsin Rahman Khan
A67: ST-131 | C67: Regression suite and backend tests | D67: Md. Nazmuz Saif | F67: Md. Tahsin Rahman Khan
A68: ST-132 | C68: Documents match the system | D68: Md. Nazmuz Saif | F68: Md. Tahsin Rahman Khan
A69: ST-133 | C69: Demo rehearsal and bug-fix buffer | D69: Md. Nazmuz Saif | F69: Md. Tahsin Rahman Khan
A70: ST-134 | C70: Analytics page | D70: Montasim Kabir Mahin | F70: Md. Nazmuz Saif
A71: ST-135 | C71: Audit Log and Audit Log page | D71: Md. Tahsin Rahman Khan | F71: Montasim Kabir Mahin
A72: ST-136 | C72: Billing page | D72: Sadia Jahan Disha | F72: Fawjiya Fahima Eifa
A73: ST-137 | C73: Monthly attendance calendar | D73: Fawjiya Fahima Eifa | F73: Sadia Jahan Disha
A75: Overall Testing — Selenium Cross-Review QA Pass (each tester tests another member's story)
A76: Story ID | B76: Test Case No. | C76: Test Case | D76: Tester | E76: Estimate (hrs) | F76: Result
A77: ST-129 | B77: TC-71 | C77: [Selenium] Apply for leave as an Employee when the company has a leave Approval Chain — expect the request Pending and visible in the approver's Pending Approvals page and Action Inbox | D77: Md. Tahsin Rahman Khan | E77: 1.5 | F77: Not Run
A78: ST-129 | B78: TC-72 | C78: [Selenium] As the approver approve the last step — expect the leave Approved, a Notification for the applicant, and the days used in the leave balance | D78: Md. Tahsin Rahman Khan | E78: 1.5 | F78: Not Run
A79: ST-129 | B79: TC-73 | C79: [Selenium] As the approver reject a leave request with a comment — expect it Rejected, the days back in the balance, and the comment shown to the applicant | D79: Md. Tahsin Rahman Khan | E79: 1.5 | F79: Not Run
A80: ST-130 | B80: TC-74 | C80: [Selenium] After running the demo data command log in as the CEO, a Manager, HR, an Accountant and an Employee — expect each dashboard to show real numbers and charts | D80: Md. Tahsin Rahman Khan | E80: 1.5 | F80: Not Run
A81: ST-130 | B81: TC-75 | C81: [Selenium] Run the demo data command a second time — expect no duplicate Employees, Departments or Tasks on their pages | D81: Md. Tahsin Rahman Khan | E81: 1.5 | F81: Not Run
A82: ST-131 | B82: TC-76 | C82: [Selenium] Run the single regression command from a clean checkout — expect a pass or fail line for every test case, and a non-zero exit code when one test is made to fail | D82: Md. Tahsin Rahman Khan | E82: 1.5 | F82: Not Run
A83: ST-132 | B83: TC-77 | C83: [Review] Compare every endpoint in the SDS API table with the running API — expect none missing and none extra | D83: Md. Tahsin Rahman Khan | E83: 1.5 | F83: Not Run
A84: ST-132 | B84: TC-78 | C84: [Review] Open the SRS requirements traceability table — expect every requirement marked Done, Partly or Not built, each with the story that delivered it | D84: Md. Tahsin Rahman Khan | E84: 1.5 | F84: Not Run
A85: ST-133 | B85: TC-79 | C85: [Rehearsal] Follow the demo script on a clean install with demo data — expect every step to work and the whole run to take about 15 minutes | D85: Md. Tahsin Rahman Khan | E85: 1.5 | F85: Not Run
A86: ST-133 | B86: TC-80 | C86: [Rehearsal] Run both test suites, npm run lint and npm run build on the final build — expect everything to pass | D86: Md. Tahsin Rahman Khan | E86: 1.5 | F86: Not Run
A87: ST-134 | B87: TC-81 | C87: [Selenium] Log in as a CEO and open Analytics — expect MetricCards, the attendance line chart and the tasks-by-department bar chart | D87: Md. Nazmuz Saif | E87: 1.5 | F87: Passed
A88: ST-134 | B88: TC-82 | C88: [Selenium] Log in as an Employee without the analytics Permission — expect no Analytics menu item and the page address blocked | D88: Md. Nazmuz Saif | E88: 1.5 | F88: Passed
... A95: ST-137 | B95: TC-89 | C95: [Selenium] Move to the previous month and look at a day of approved leave — expect the calendar to change month and show that day as On Leave | D95: Sadia Jahan Disha | E95: 1.5 | F95: Not Run
A97: Coordination Tasks (Mahin)
A98: Task | B98: Owner | C98: Estimate (hrs) | D98: Status
A99: Sprint 5 planning session — select the last stories from the backlog, confirm scope and the date after which no new feature is added | B99: Montasim Kabir Mahin | C99: 2 | D99: To Do
A100: Daily coordination and progress tracking | B100: Montasim Kabir Mahin | C100: 3 | D100: To Do
A101: Cross-test hand-off tracking — confirm each story is tested by a non-owner | B101: Montasim Kabir Mahin | C101: 1 | D101: To Do
A102: Demo day planning — confirm who presents which part and when the two rehearsals happen | B102: Montasim Kabir Mahin | C102: 2 | D102: To Do
A103: Sprint 5 review and final retrospective facilitation | B103: Montasim Kabir Mahin | C103: 2 | D103: To Do
B105: Total Implementation Hours | E105: =SUM(E23:E61) -> 99
B106: Total QA Hours | E106: =SUM(E77:E95) -> 28.5
A107: Total Coordination Hours | C107: =SUM(C99:C103) -> 10

Sheet Sprint 6 Brief
A1: Ordinis — Sprint 6 Brief (read this first)
A2: Written so that a new conversation can pick up Sprint 6 from this workbook alone. Dates: Oct 21 – Nov 4. Stories ST-138 to ST-155, backlog PB-41 to PB-58, test cases TC-90 to TC-132.
A4: 1. Context
A5: Purpose of this tab | C5: Start here. Then read the Sprint 6 tab (stories, tasks, test cases, cross-test table) and the Gap Register tab (the 23 gaps Saif listed on Oct 20, plus 8 more found while analysing them; every gap points to the story that fixes it). The Product Backlog tab has PB-41 to PB-58 for these stories.
A6: The project in short | C6: Ordinis is a multi-tenant Organization Operating System: a Django REST Framework backend (14 apps, SQLite in development) and a React + Vite + Tailwind frontend. Each company builds its own hierarchy, Roles and Permissions, approval chains, tasks, attendance and leave, payroll and billing. A Platform Admin runs the platform and can see a company only through the Break-Glass process (request, company approval, time limit, read-only, logged). Rules that must hold in every story: every query is filtered by company and another company's id is a 404; access is checked by Permission codename, never by job title; business rules live in services.py; every API answers in the standard envelope {success, data, message} or {success, error: {code, message, field_errors}}.
A7: State at the end of Sprint 5 | C7: Treated as fully complete, as Saif stated on Oct 20: ST-129 to ST-137 Done and TC-71 to TC-89 Passed, including Analytics (ST-134) and the monthly attendance calendar (ST-137). At the last verified build the backend had 568 passing tests, makemigrations --check was clean, and generate_docs and check_docs matched the code. The Sprint 5 tab and the Sprint 5 rows of the Product Backlog were left exactly as they were; update their statuses when they are really true.
A8: Sprint 6 goal | C8: Make the product ready to run as a business and to manage: fix the Roles bugs, give people real names, profiles and safe passwords, add detail pages and team attendance, finish billing (timeline, registration with plan choice, manual payment approval, renewal, upgrade) and give the Platform Admin company details, notes, requests and a dashboard.
A9: Size and the five-sprint rule | C9: 18 stories and 102 story points, against 9 stories and 40 points in Sprint 5, so it is planned as 15 days. Implementation is about 232 hours (workload table at the bottom). The course plan fixed five sprints, so Sprint 6 is an extra improvement sprint after them; decide how to present it.
A11: 2. How the stories are ordered and owned
A12: Order | C12: The stories on the Sprint 6 tab are listed in the order they are implemented, one after another. Every story needs only stories above it, so you can start at the top and work down without jumping. The order table in section 3 shows what each story needs and a target finish date.
A13: Owners | C13: One serial, as Saif asked: the first ten stories (ST-138 to ST-147) are Saif's, then two each for Mahin, Tahsin, Disha and Eifa in that order, so Eifa has the last two. Saif keeps the foundations and the money core (catalog, names and profile, passwords, subscription period, payments, registration). ST-155 (regression, documents, demo script) has to come last, so by this serial it is Eifa's; swap it with Saif if you prefer. Change the Owner column freely.
A14: Standing rules (unchanged) | C14: One story has one owner and is an isolated piece of work. Every story is tested with Selenium by someone other than its owner; tester rotation: Mahin's code is tested by Saif, Tahsin's by Mahin, Saif's by Tahsin, Eifa's by Disha, Disha's by Eifa. A story is Done only when its code is written, self-tested and its Selenium test cases pass. Commits carry their real date. Story IDs continue from ST-138, backlog from PB-41, test cases from TC-90. Migrations: add a new migration, never regenerate old ones. Documents: the generated parts come from python manage.py generate_docs and are checked by check_docs. Test commands: python regression.py backend and python regression.py selenium, plus npm run lint and npm run build. "docs" means a Word file.
A16: 3. Order table (implement from top to bottom)
A17: Order | B17: Story | C17: Owner | D17: Tier | E17: Needs (stories above) | F17: Target finish | G17: Notes
A18: 1 | B18: ST-138 — Permission catalog in code and Roles page bug fix | C18: Md. Nazmuz Saif | D18: Must | E18: — | F18: Oct 21 | G18: First: every later Permission (team attendance, billing) is added to this catalog.
A19: 2 | B19: ST-139 — Roles v2: sections, role detail and role edit | C19: Md. Nazmuz Saif | D19: Must | E19: ST-138 | F19: Oct 22 | G19: Right after ST-138: the Roles page builds on the new catalog and descriptions.
A20: 3 | B20: ST-140 — Names, profile data and the profile API | C20: Md. Nazmuz Saif | D20: Must | E20: — | F20: Oct 23 | G20: Gives every later story real names and the profile API.
A21: 4 | B21: ST-141 — My Profile page for every user | C21: Md. Nazmuz Saif | D21: Must | E21: ST-140 | F21: Oct 23 | G21: UI for the profile API from ST-140.
A22: 5 | B22: ST-142 — Password safety: change password and temporary password | C22: Md. Nazmuz Saif | D22: Must | E22: ST-141, ST-140 | F22: Oct 24 | G22: Adds the password forms to the My Profile page from ST-141.
A23: 6 | B23: ST-143 — Employee detail page v2 | C23: Md. Nazmuz Saif | D23: Must | E23: ST-138, ST-140 | F23: Oct 25 | G23: Needs the catalog (ST-138) for effective Permissions and the names and profile fields (ST-140).
A24: 7 | B24: ST-144 — Team attendance with employee dropdown | C24: Md. Nazmuz Saif | D24: Must | E24: ST-138, ST-140 | F24: Oct 26 | G24: Needs the catalog (ST-138), names (ST-140) and the Sprint 5 calendar (ST-137).
A25: 8 | B25: ST-145 — Subscription period, days left, reminders and restricted mode | C25: Md. Nazmuz Saif | D25: Must | E25: — | F25: Oct 27 | G25: Start of the billing chain; keep register_company and seed data working.
A26: 9 | B26: ST-146 — Duration pricing, manual payment submission and admin approval | C26: Md. Nazmuz Saif | D26: Must | E26: ST-145 | F26: Oct 28 | G26: Core of billing: price, payment submission, approval, invoice. Needs the period fields from ST-145.
A27: 10 | B27: ST-147 — Registration with plan choice, payment and waiting page | C27: Md. Nazmuz Saif | D27: Must | E27: ST-145, ST-146 | F27: Oct 29 | G27: Its second test case needs the Payments page (ST-148); run it after ST-148 is done, or approve through the API.
A28: 11 | B28: ST-148 — Platform Admin payments review and subscriptions timeline | C28: Montasim Kabir Mahin | D28: Must | E28: ST-146 | F28: Oct 29 | G28: Gives the Platform Admin the UI to approve payments.
A29: 12 | B29: ST-149 — Company Billing timeline, renewal and invoice detail | C29: Montasim Kabir Mahin | D29: Must | E29: ST-145, ST-146 | F29: Oct 31 | G29: Includes the renewal invoice job (backend 3 h).
... A35: 18 | B35: ST-155 — Sprint 6 regression, documents and demo script | C35: Fawjiya Fahima Eifa | D35: Must | E35: all Must stories | F35: Nov 4 | G35: Last: updates tests, documents and demo script, then the rehearsal.
A36: Target finish | C36: Spreads the story points evenly over the 15 days (Oct 21 is day 1, Nov 4 day 15). It is a pace to aim for, not a promise; a bigger story takes its own time.
A38: 4. Key design decisions (the reasons, so nobody re-argues them)
A39: D1 Permission catalog in code | C39: One list in rbac/catalog.py (codename, name, module, description) synced on migrate. A new Permission is one line and the CEO role receives it through the existing sync. A Permission is added only together with the feature it protects. A test checks that every codename used in the views is in the catalog.
A40: D2 Names and profile | C40: full_name lives on User (so the Platform Admin has one); phone, address, emergency contact and joined on live on Employee. The profile endpoint edits only a whitelist; it can never change email, department, designation, manager, Roles or salary.
A41: D3 Temporary password | C41: The CEO never types an employee's password. The system makes a one-time temporary password, shows it once, and the employee must change it at first login (PASSWORD_CHANGE_REQUIRED). Creating with an explicit password still works, so older tests keep passing.
A42: D4 Who sees what on a person | C42: Contact details only for the person, their managers and manage_employees; salary only with manage_finance; task titles on a Department page only for people who may see those tasks, others see counts. This keeps FR-13.
A43: D5 Days left is computed | C43: Days left = end date minus today in the company time zone. It is never stored or decremented by a job, so a missed job cannot make it wrong. The daily process_subscriptions command only sends reminders and sets the expired status; the same check also runs on every request.
A44: D6 Restricted mode, not suspension | C44: A company that is pending payment or expired can log in but only Billing, payment, profile, support and logout work (SUBSCRIPTION_RESTRICTED). Suspend (is_active false) stays a full block for misuse. Without this an unpaid company could not even reach the page where it pays.
A45: D7 Manual payments | C45: The amount is always computed on the server. A transaction id is unique per method. One pending submission per company. Approval is idempotent (locked row). A company can never approve its own payment. The invoice is created on approval, not when the form is submitted.
A46: D8 Renewal | C46: The renewal invoice is created 7 days before the end so the client sees what to pay; paying and approval extend from the old end date, so no days are lost.
A47: D9 Pricing | C47: Price = plan monthly price × months (1 to 36); 12 months costs the price of 10. Current plan prices are placeholders: Basic 1500, Professional 5000, Enterprise 15000 BDT a month (employee limits 10, 50, unlimited).
A48: D10 Upgrade | C48: Extra amount = (new monthly price − old monthly price) × days left ÷ 30, rounded to the taka; the end date does not change. A lower plan only at the next renewal and only if the team fits.
A49: D11 Platform Admin privacy | C49: The company detail page and the dashboard show counts, dates, money and the owner's contact only, never employee names, tasks, attendance or salary. Break-Glass remains the only way into company data.
A50: D12 Reminders | C50: In-app Notifications and a banner only (7, 3 and 1 days before the end); there is no email or SMS channel yet.
A52: 5. Defaults, cut line, risks
A53: Defaults (one constant each) | C53: Grace period 3 days after the end date; reminders at 7, 3 and 1 days; yearly discount 12 months for the price of 10; months 1 to 36; payment methods bKash, Nagad, bank and cash; no free trial (a new company must pay before it starts). Changing any of these touches only ST-145 and ST-146.
A54: Cut line | C54: Must stories carry the sprint: ST-138, ST-139, ST-140, ST-141, ST-142, ST-143, ST-144, ST-145, ST-146, ST-147, ST-148, ST-149, ST-150, ST-154, ST-155. Should stories can move to Sprint 7 without breaking anything above them: ST-151, ST-152, ST-153. Decide at the Oct 28 check (Mahin's coordination task).
A55: Risks | C55: 1) Because the order is strict, a slip delays the stories below it. Saif's ten come first and carry about 130 implementation hours; the teammates' eight stories wait for them, and ST-138, ST-140, ST-145 and ST-146 matter most. 2) The size: 232 implementation hours in 15 days. 3) Payments are verified by a person, not a gateway, so the Platform Admin must check the transaction before approving. 4) Registration changes make old tests and Selenium helpers fail until they are updated (X-08). 5) Time zones: days left and reminders use the company time zone.
A56: Definition of Done | C56: Code written and merged; the story's own tests pass; python regression.py backend still passes; npm run lint and npm run build pass; the Selenium test cases of the story pass for the tester; documents regenerate cleanly (generate_docs, check_docs); the story status is changed to Done only after that.
A57: Out of scope for Sprint 6 | C57: A real payment gateway (bKash or Nagad API), email or SMS, multi-factor authentication and password reset by email, field-level encryption, Projects, Expense and Reimbursement, and the Layer 3 modules. They stay future work.
A58: How to start in a new conversation | C58: Give the new conversation this workbook, the latest Ordinis-Submission.zip and the continuity instruction. Ask it to read this tab, then start with ST-138 (the first row of the order table), one step at a time, with a Django shell or test run after each step and a commit at the end of each session.
A60: 6. Workload by owner (formulas read the Sprint 6 tab)
A61: Owner | C61: Stories | D61: Points | E61: Implementation hours | F61: QA hours | G61: Stories (ids)
A62: Md. Nazmuz Saif | C62: =COUNTIF('Sprint 6'!$D$7:$D$24,A62) -> 10 | D62: =SUMIF('Sprint 6'!$D$7:$D$24,A62,'Sprint 6'!$E$7:$E$24) -> 56 | E62: =SUMIF('Sprint 6'!$D$32:$D$114,A62,'Sprint 6'!$E$32:$E$114) -> 130 | F62: =SUMIF('Sprint 6'!$D$139:$D$181,A62,'Sprint 6'!$E$139:$E$181) -> 9 | G62: ST-138, ST-139, ST-140, ST-141, ST-142, ST-143, ST-144, ST-145, ST-146, ST-147
A63: Montasim Kabir Mahin | C63: =COUNTIF('Sprint 6'!$D$7:$D$24,A63) -> 2 | D63: =SUMIF('Sprint 6'!$D$7:$D$24,A63,'Sprint 6'!$E$7:$E$24) -> 13 | E63: =SUMIF('Sprint 6'!$D$32:$D$114,A63,'Sprint 6'!$E$32:$E$114) -> 25 | F63: =SUMIF('Sprint 6'!$D$139:$D$181,A63,'Sprint 6'!$E$139:$E$181) -> 7.5 | G63: ST-148, ST-149
A64: Md. Tahsin Rahman Khan | C64: =COUNTIF('Sprint 6'!$D$7:$D$24,A64) -> 2 | D64: =SUMIF('Sprint 6'!$D$7:$D$24,A64,'Sprint 6'!$E$7:$E$24) -> 13 | E64: =SUMIF('Sprint 6'!$D$32:$D$114,A64,'Sprint 6'!$E$32:$E$114) -> 27 | F64: =SUMIF('Sprint 6'!$D$139:$D$181,A64,'Sprint 6'!$E$139:$E$181) -> 33 | G64: ST-150, ST-151
A65: Sadia Jahan Disha | C65: =COUNTIF('Sprint 6'!$D$7:$D$24,A65) -> 2 | D65: =SUMIF('Sprint 6'!$D$7:$D$24,A65,'Sprint 6'!$E$7:$E$24) -> 10 | E65: =SUMIF('Sprint 6'!$D$32:$D$114,A65,'Sprint 6'!$E$32:$E$114) -> 23 | F65: =SUMIF('Sprint 6'!$D$139:$D$181,A65,'Sprint 6'!$E$139:$E$181) -> 9 | G65: ST-152, ST-153
A66: Fawjiya Fahima Eifa | C66: =COUNTIF('Sprint 6'!$D$7:$D$24,A66) -> 2 | D66: =SUMIF('Sprint 6'!$D$7:$D$24,A66,'Sprint 6'!$E$7:$E$24) -> 10 | E66: =SUMIF('Sprint 6'!$D$32:$D$114,A66,'Sprint 6'!$E$32:$E$114) -> 27 | F66: =SUMIF('Sprint 6'!$D$139:$D$181,A66,'Sprint 6'!$E$139:$E$181) -> 6 | G66: ST-154, ST-155
A67: Total | C67: =SUM(C62:C66) -> 18 | D67: =SUM(D62:D66) -> 102 | E67: =SUM(E62:E66) -> 232 | F67: =SUM(F62:F66) -> 64.5 | G67: Sprint 5 for comparison: 9 stories, 40 points, 99 implementation hours, 28.5 QA hours

Sheet Sprint 6
A1: Ordinis — Sprint 6 Planning
A2: Sprint Duration: Oct 21 – Nov 4
A3: Sprint Goal: Fix the Roles bugs and give every person a real name, a profile and a safe password. Give every Role, Employee, Department and Designation a detail page, let managers see team attendance, and finish billing: subscription timeline, registration with plan choice and manual payment approval, renewals and plan upgrades. Give the Platform Admin company details, notes, access and support requests and a dashboard, then update the tests, documents and demo script.
A5: Selected Stories for this Sprint
A6: Story ID | B6: User Story | D6: Owner | E6: Story Points | F6: Acceptance Criteria
A7: ST-138 | B7: As a CEO, I want every Permission to have a clear name, a plain-language description and a module, kept in one place in the code, and the Roles page to offer only real Permissions, so that a Role I create keeps every Permission I tick and I know what each one allows. (PB-41) | D7: Md. Nazmuz Saif | E7: 5 | F7: - A permission catalog in the code (rbac/catalog.py) lists every Permission with codename, name, module and a plain-language description; running migrate adds missing rows and refreshes names and descriptions, so a new Permission no longer needs its own migration; the CEO system Role still receives every Permission - The Permission model has a description field, and GET /api/v1/rbac/permissions/ returns codename, name, module and description - The Roles page builds its Permission list only from that API; the hardcoded list is removed (six of its names, such as approve_leave and view_finance, do not exist in the backend and were silently dropped) - Creating a Role with N Permissions saves exactly N, and the existing-Roles list shows all N grouped by module; if the server did not save a ticked Permission the page says so - A test fails when a ViewSet uses a permission_required codename that is not in the catalog
A8: ST-139 | B8: As a CEO, I want a Roles page with Permissions in sections, a detail page for each Role that explains what every Permission lets people do, and the ability to edit a Role, so that I can design access without guessing. (PB-42) | D8: Md. Nazmuz Saif | E8: 5 | F8: - The create and edit Role form shows Permissions in collapsible module sections, each with its name, a one-line description and a Select all per section, and a counter of how many are chosen - Each Role has a detail page (/roles/:id) with its description, its Permissions grouped by module with their descriptions, and the employees who hold it - A Role can be edited (name, description, Permissions); the CEO system Role cannot be edited or deleted and the page says why; before saving the page says how many employees the change affects - The existing-Roles list shows the real Permission count and the first few names with +N more - Deleting a Role that employees still hold is refused with code ROLE_IN_USE and a clear message; the Role stays in the list
A9: ST-140 | B9: As an employee, I want my full name and profile details stored and editable by me, so that the system shows real names everywhere and I keep my own details current. (PB-43) | D9: Md. Nazmuz Saif | E9: 5 | F9: - User gets full_name; Employee gets phone, address, emergency contact name and phone, and joined on; registration asks for the owner's full name; creating and editing an Employee takes the full name; seed_demo_data gives every demo person a name - GET and PATCH /api/v1/auth/profile/ work for the logged-in user, the Platform Admin included; only full name, phone, address and emergency contact can be changed; email, department, designation, manager, Roles and salary can never be changed through it - Every serializer that returns an employee email also returns the employee name, and every page shows the full name first (with code or email in small text) - Old rows without a name still work (the name may be empty and the page falls back to the email)
A10: ST-141 | B10: As any user (employee, CEO or Platform Admin), I want a My Profile page where I see and edit my own details, so that I keep my information current myself. (PB-44) | D10: Md. Nazmuz Saif | E10: 5 | F10: - The user menu has My Profile; the page shows full name, email (read-only), designation, department, manager and company (read-only) and phone, address and emergency contact (editable); the Platform Admin sees the same page without the company fields - Saving shows success or the field errors from the server; leaving the page with unsaved changes asks first - A user opening another user's profile address is not possible: the page only ever loads the logged-in user's own data
A11: ST-142 | B11: As a CEO and as an employee, I want a safe way to change my password and a temporary password for new employees, so that nobody has to share a password. (PB-45) | D11: Md. Nazmuz Saif | E11: 5 | F11: - POST /api/v1/auth/change-password/ needs the current password, applies the password rules and ends the user's other sessions (blacklists their other refresh tokens); the My Profile page has the form (current, new, confirm) and shows the server message for a wrong current password - When the CEO creates an Employee without typing a password, the system makes a one-time temporary password, returns it once, and the Employee must change it at first login: until then every endpoint except change-password, profile, me and logout answers 403 with code PASSWORD_CHANGE_REQUIRED; creating with an explicit password still works as before - After login with a temporary password the user is sent to My Profile and cannot open any other page until the password is changed - The Employee create form no longer gets email and password filled in by the browser, and after creating an Employee shows the temporary password once with a Copy button
A12: ST-143 | B12: As a CEO or HR user, I want an Employee detail page with the full profile and the Permissions that person really has, so that I can see exactly who someone is and what they can do. (PB-46) | D12: Md. Nazmuz Saif | E12: 5 | F12: - The page shows full name, email, code, phone, address, emergency contact, joined on, department, designation, manager, direct reports and the chain of managers - A Permissions section lists each Role the person holds and under it the effective Permissions grouped by module with descriptions; a person with no Role shows No Permissions - Phone, address and emergency contact are visible only to the person, their managers and holders of manage_employees; everyone else sees name, designation and department; salary and payroll lines only with manage_finance - A user with manage_employees can edit these fields from the page
A13: ST-144 | B13: As a CEO or a manager with the Permission, I want to pick an employee from a dropdown and see their attendance for a month, so that I know how many days they came and at what times. (PB-47) | D13: Md. Nazmuz Saif | E13: 5 | F13: - A new Permission view_team_attendance is added to the catalog with a description; the CEO role holds it; a user with it sees every employee of the company, a user without it sees only the people below them in the hierarchy; a user with no team sees no Team Attendance menu item - The Team Attendance page (Attendance group in the sidebar) has a searchable employee dropdown, a month picker with previous and next, the monthly calendar and the Present, Absent, On Leave and rate cards for that employee, and a table of each day's check-in, check-out and hours worked - The month shows days present and total hours; a day with no check-out shows no check-out - GET /attendance/attendance/team/?employee=&month= answers 404 (not 403) for an employee outside the user's scope or in another company - My Attendance still shows only the user's own data
A14: ST-145 | B14: As the Platform Owner, I want every company's subscription to have a start and end date, a days-left count, automatic reminders before it ends and a restricted mode after it ends, so that unpaid companies stop using the product without being locked out of paying. (PB-48) | D14: Md. Nazmuz Saif | E14: 8 | F14: - Subscription gets current_period_start, current_period_end, billing_months and the status pending_payment, active, expired or cancelled; days left are computed from today's date in the company time zone, never stored or counted down by a job - python manage.py process_subscriptions (run daily) sends an in-app Notification to the CEO and to billing holders 7, 3 and 1 days before the end (once per threshold) and moves a subscription to expired 3 days after its end date; running it twice changes nothing more - Restricted mode: a company with status pending_payment or expired can log in, but every endpoint except login, refresh, logout, me, profile, change-password, billing, payments, plans and support answers 403 with code SUBSCRIPTION_RESTRICTED; the frontend then shows only the Billing pages and a banner; Suspend (is_active false) still blocks everything - The check also runs on every request, so a company past its end date is restricted even if the daily job did not run - seed_demo_data and the existing tests keep working: demo companies are active with long periods and the register_company test helper activates the subscription
A15: ST-146 | B15: As a company owner, I want to choose a plan for any number of months, pay by bKash, Nagad or bank transfer outside the system and submit the payment details, so that the platform team can check and approve it and my plan starts. (PB-49) | D15: Md. Nazmuz Saif | E15: 8 | F15: - Price = plan monthly price × months, 1 to 36 months, and 12 months costs the price of 10; GET /billing/quote/?plan=&months= returns the amount, the discount and the period; the amount is always computed on the server - PaymentSubmission records company, plan, months, amount, method (bkash, nagad, bank, cash), payer name, payer number, transaction id, kind (new, renewal, upgrade), status (pending, approved, rejected), reviewed by, reviewed at and the review note; a transaction id can be used once per method; a company has one pending submission at a time - A new Permission manage_billing (in the catalog) lets a company submit and read its own payments; the Platform Admin lists all, approves, or rejects with a note - Approving is idempotent (locked row): it activates or extends the subscription (a renewal extends from the old end date, so no days are lost), creates the paid Invoice with the next number and notifies the company; rejecting notifies with the note; approving twice changes nothing - Every approval and rejection is audit-logged and written to PlatformActionLog; a company can never approve its own payment
A16: ST-147 | B16: As a new client, I want to register, choose a plan and duration, pay and submit my payment details, and wait for approval, so that my company starts only after my payment is checked. (PB-50) | D16: Md. Nazmuz Saif | E16: 5 | F16: - Registering (company name, owner full name, email, password) creates the company in pending_payment and signs the owner in; the owner lands on Choose a plan: cards for Basic, Professional and Enterprise with employee limit and monthly price, and a months selector (1, 3, 6, 12 or custom 1 to 36) with a live total from the quote endpoint - Next opens the payment page: how to pay (bKash, Nagad, bank or manual instructions read from the server settings) and a form with method, payer name, payer number and transaction id, with the amount shown read-only - After submit a waiting page shows Waiting for approval and refreshes itself; a rejected payment shows the admin's note and a form to submit again; an approved one sends the owner to the dashboard - Companies registered before this change and the demo companies are unaffected
A17: ST-148 | B17: As the Platform Owner, I want a Payments page to review the payments companies submit and a Subscriptions page that shows every company's days left, so that I approve what I verified and see who expires soon. (PB-51) | D17: Montasim Kabir Mahin | E17: 5 | F17: - The Payments page lists submissions (newest first, Pending by default) with company, plan, months, amount, method, payer, number, transaction id, kind and status, with filters; a detail panel; Approve (with confirm) and Reject (note required); after approval it shows the new end date and the invoice number - The Subscriptions page lists every company with plan, status, end date and days left (7 days or fewer amber, expired red), sorted by days left, with filters Expiring in 7 days and Expired or Restricted - The platform sidebar has Payments with a count of pending submissions, and Subscriptions - Only a Platform Admin can open these pages or call their endpoints
A18: ST-149 | B18: As a CEO, I want a Billing timeline showing how many days my plan has left, a Renew button with an invoice to pay, and a detail page for every invoice, so that I always know when and how much to pay. (PB-52) | D18: Montasim Kabir Mahin | E18: 8 | F18: - The top of the Billing page is a timeline card: plan, start and end dates, a progress bar, N days left in large text and a status (Active, Expiring soon at 7 days or fewer, Restricted) - Seven days before the end the daily job creates the renewal Invoice (open, due on the end date), once only; Renew shows that invoice and its amount with the same payment form as registration, tied to the invoice; a pending banner shows after submit; after approval the invoice is Paid and the end date moves - The invoice list shows number, period, amount and status; each row opens /settings/billing/invoices/:id with number, company, plan, period, months, amount, currency, issue, due and paid dates, payment method, transaction id and status, and a Print button - Another company's invoice id is a 404; the timeline needs view_billing and paying needs manage_billing
... A24: ST-155 | B24: As a Team, I want the tests, documents and demo script to match the Sprint 6 system and one more full rehearsal, so that the final build is ready to present. (PB-58) | D24: Fawjiya Fahima Eifa | E24: 5 | F24: - python regression.py backend and python regression.py selenium pass, and npm run lint and npm run build pass; older Selenium tests that registered a company or typed a password are updated for the registration, names and menus of Sprint 6 - New requirements for profile and password, Permission descriptions and Role editing, Department and Designation detail, team attendance, subscription period and restricted mode, manual payment approval, plan change and the Platform Admin dashboard are in the traceability list with code evidence and show Done in SRS Section 7.2 - SRS, SDS (profile, catalog and billing sections), project structure, ER diagram and design system match the code (generate_docs and check_docs pass) - The demo script (Word) covers the new flows (register, pay and approve; profile; Role detail; Department detail; team attendance; billing timeline; Platform Admin dashboard) and has been rehearsed once on a clean install, with a bug-fix buffer
A26: Carried Over from Sprint 5
A27: Story ID | B27: Category | C27: Task | D27: Owner | E27: Estimate (hrs) | F27: Status
A28: — | B28: — | C28: Nothing is carried over: Sprint 5 is treated as complete (stated by Saif on Oct 20). If any Sprint 5 story turns out not to be Done, add it here as a story owned by Saif. | D28: — | E28: 0 | F28: Done
A30: Task Breakdown (Implementation)
A31: Story ID | B31: Category | C31: Task | D31: Owner | E31: Estimate (hrs) | F31: Status
A32: ST-138 | B32: Design | C32: Design the catalog fields (codename, name, module, description), the sync step that runs on migrate before sync_system_roles, and the module groups | D32: Md. Nazmuz Saif | E32: 1 | F32: To Do
A33: ST-138 | B33: Database | C33: Add Permission.description with a migration and fill it for the 14 current Permissions | D33: Md. Nazmuz Saif | E33: 1 | F33: To Do
A34: ST-138 | B34: Backend | C34: Write rbac/catalog.py and the sync; return description from the Permission API; keep the CEO role holding every Permission | D34: Md. Nazmuz Saif | E34: 3 | F34: To Do
A35: ST-138 | B35: Backend | C35: Write the test that every permission_required codename used in the views exists in the catalog | D35: Md. Nazmuz Saif | E35: 2 | F35: To Do
A36: ST-138 | B36: Frontend | C36: Roles page: remove the hardcoded list, load Permissions from the API, group by module, fix the existing-Roles list so it shows every saved Permission | D36: Md. Nazmuz Saif | E36: 3 | F36: To Do
A37: ST-138 | B37: Self-Test | C37: Self-test a Role with all, one and no Permissions; migrate on a fresh and on an existing database; the CEO role holds every Permission | D37: Md. Nazmuz Saif | E37: 2 | F37: To Do
A38: ST-139 | B38: Design | C38: Design the sectioned picker, the Role detail page and the edit flow, including the locked CEO Role | D38: Md. Nazmuz Saif | E38: 1 | F38: To Do
A39: ST-139 | B39: Backend | C39: Return employee_count and the holders of a Role; refuse deleting a Role in use (ROLE_IN_USE) | D39: Md. Nazmuz Saif | E39: 2 | F39: To Do
A40: ST-139 | B40: Frontend | C40: Build the sectioned picker, the Role detail page, edit mode and the new Roles list | D40: Md. Nazmuz Saif | E40: 6 | F40: To Do
A41: ST-139 | B41: Self-Test | C41: Self-test edit add and remove, the locked CEO Role, delete in use, another company's Role | D41: Md. Nazmuz Saif | E41: 2 | F41: To Do
A42: ST-140 | B42: Design | C42: Design the profile fields, the editable whitelist and the display rule for names | D42: Md. Nazmuz Saif | E42: 1 | F42: To Do
A43: ST-140 | B43: Database | C43: Add full_name to User and the profile fields to Employee, with migrations (blank allowed for old rows) | D43: Md. Nazmuz Saif | E43: 2 | F43: To Do
... A114: ST-155 | B114: Self-Test | C114: Run both test suites, npm run lint and npm run build on the final build and tag the release | D114: Fawjiya Fahima Eifa | E114: 2 | F114: To Do
A116: Cross-Test Assignment (every story is tested by someone other than its owner)
A117: Story ID | C117: Story | D117: Code Owner | F117: Selenium Tester
A118: ST-138 | C118: Permission catalog in code and Roles page bug fix | D118: Md. Nazmuz Saif | F118: Md. Tahsin Rahman Khan
A119: ST-139 | C119: Roles v2: sections, role detail and role edit | D119: Md. Nazmuz Saif | F119: Md. Tahsin Rahman Khan
A120: ST-140 | C120: Names, profile data and the profile API | D120: Md. Nazmuz Saif | F120: Md. Tahsin Rahman Khan
A121: ST-141 | C121: My Profile page for every user | D121: Md. Nazmuz Saif | F121: Md. Tahsin Rahman Khan
A122: ST-142 | C122: Password safety: change password and temporary password | D122: Md. Nazmuz Saif | F122: Md. Tahsin Rahman Khan
A123: ST-143 | C123: Employee detail page v2 | D123: Md. Nazmuz Saif | F123: Md. Tahsin Rahman Khan
A124: ST-144 | C124: Team attendance with employee dropdown | D124: Md. Nazmuz Saif | F124: Md. Tahsin Rahman Khan
A125: ST-145 | C125: Subscription period, days left, reminders and restricted mode | D125: Md. Nazmuz Saif | F125: Md. Tahsin Rahman Khan
A126: ST-146 | C126: Duration pricing, manual payment submission and admin approval | D126: Md. Nazmuz Saif | F126: Md. Tahsin Rahman Khan
A127: ST-147 | C127: Registration with plan choice, payment and waiting page | D127: Md. Nazmuz Saif | F127: Md. Tahsin Rahman Khan
A128: ST-148 | C128: Platform Admin payments review and subscriptions timeline | D128: Montasim Kabir Mahin | F128: Md. Nazmuz Saif
... A135: ST-155 | C135: Sprint 6 regression, documents and demo script | D135: Fawjiya Fahima Eifa | F135: Sadia Jahan Disha
A137: Overall Testing — Selenium Cross-Review QA Pass (each tester tests another member's story)
A138: Story ID | B138: Test Case No. | C138: Test Case | D138: Tester | E138: Estimate (hrs) | F138: Result
A139: ST-138 | B139: TC-90 | C139: [Selenium] As the CEO create a Role and tick one Permission from every module — expect the new Role card to list all of them, not four | D139: Md. Tahsin Rahman Khan | E139: 1.5 | F139: Not Run
A140: ST-138 | B140: TC-91 | C140: [Selenium] Open the Roles page — expect Permissions grouped by module, each with a description, and every name present in the backend | D140: Md. Tahsin Rahman Khan | E140: 1.5 | F140: Not Run
A141: ST-139 | B141: TC-92 | C141: [Selenium] As the CEO open a Role's detail page — expect Permissions grouped by module with descriptions and the list of employees who hold it | D141: Md. Tahsin Rahman Khan | E141: 1.5 | F141: Not Run
A142: ST-139 | B142: TC-93 | C142: [Selenium] Edit a Role: add and remove Permissions and save — expect the detail page and the Roles list to show the change; the CEO Role shows no Edit button | D142: Md. Tahsin Rahman Khan | E142: 1.5 | F142: Not Run
A143: ST-139 | B143: TC-94 | C143: [Selenium] Delete a Role that an Employee holds — expect a clear refusal and the Role still listed | D143: Md. Tahsin Rahman Khan | E143: 1.5 | F143: Not Run
A144: ST-140 | B144: TC-95 | C144: [Selenium] Register a new company with a full name — expect the top bar and the Employees list to show that name | D144: Md. Tahsin Rahman Khan | E144: 1.5 | F144: Not Run
A145: ST-140 | B145: TC-96 | C145: [API] PATCH the profile with a new phone and also with email, department and salary — expect only the phone changed and the other fields ignored or refused | D145: Md. Tahsin Rahman Khan | E145: 1.5 | F145: Not Run
A146: ST-141 | B146: TC-97 | C146: [Selenium] Open My Profile as an Employee, change the phone number, save and reload — expect the new number and no way to edit the email | D146: Md. Tahsin Rahman Khan | E146: 1.5 | F146: Not Run
A147: ST-141 | B147: TC-98 | C147: [Selenium] Open My Profile as the Platform Admin — expect the name and contact fields and no company fields | D147: Md. Tahsin Rahman Khan | E147: 1.5 | F147: Not Run
A148: ST-142 | B148: TC-99 | C148: [Selenium] As the CEO add an Employee without typing a password — expect a temporary password shown once, and the browser not filling the email or password fields | D148: Md. Tahsin Rahman Khan | E148: 1.5 | F148: Not Run
A149: ST-142 | B149: TC-100 | C149: [Selenium] Log in as that Employee — expect to be sent to My Profile to set a new password before anything else; change it with a wrong current password first — expect an error, then success | D149: Md. Tahsin Rahman Khan | E149: 1.5 | F149: Not Run
A150: ST-142 | B150: TC-101 | C150: [Selenium] Change a password, then use an older refresh token — expect it refused | D150: Md. Tahsin Rahman Khan | E150: 1.5 | F150: Not Run
... A181: ST-155 | B181: TC-132 | C181: [Rehearsal] Run both test suites, npm run lint and npm run build on the final build — expect all to pass | D181: Sadia Jahan Disha | E181: 1.5 | F181: Not Run
A183: Coordination Tasks (Mahin)
A184: Task | D184: Owner | E184: Estimate (hrs) | F184: Status
A185: Sprint 6 planning session — confirm scope, the order of the stories (the order they are implemented), the owners and the cut line | D185: Montasim Kabir Mahin | E185: 2 | F185: To Do
A186: Daily coordination and progress tracking, with extra attention to the stories that others need: ST-138 (catalog), ST-140 (names and profile), ST-145 (subscription period) and ST-146 (payments) | D186: Montasim Kabir Mahin | E186: 4 | F186: To Do
A187: Cross-test hand-off tracking — confirm each story is tested by a non-owner and that no tester carries too many | D187: Montasim Kabir Mahin | E187: 2 | F187: To Do
A188: Mid-sprint check on Oct 28 — decide if the Should stories (ST-151, ST-152, ST-153) stay in Sprint 6 or move to Sprint 7 | D188: Montasim Kabir Mahin | E188: 1 | F188: To Do
A189: Sprint 6 review and retrospective facilitation | D189: Montasim Kabir Mahin | E189: 2 | F189: To Do
B191: Total Story Points | E191: =SUM(E7:E24) -> 102
B192: Total Implementation Hours | E192: =SUM(E32:E114) -> 232
B193: Total QA Hours | E193: =SUM(E139:E181) -> 64.5
B194: Total Coordination Hours | E194: =SUM(E185:E189) -> 11

Sheet Gap Register
A1: Ordinis — Gap Register (gaps and bugs found after Sprint 5)
A2: The 23 items Saif listed on Oct 20 (G-01 to G-23, same order as his list), checked against the code, plus 8 more found during the analysis (X-01 to X-08). Every row names the Sprint 6 story that fixes it.
A4: Summary
A5: Gaps from your list | E5: =COUNTA(A13:A35) -> 23
A6: Extra findings | E6: =COUNTA(A36:A43) -> 8
A7: Open | E7: =COUNTIF(L13:L43,"Open") -> 31
A8: Fixed | E8: =COUNTIF(L13:L43,"Fixed") -> 0
A9: High priority | E9: =COUNTIF(H13:H43,"High") -> 15
A10: Bugs (G-03, G-08, X-02) | E10: =COUNTIF(D13:D43,"Bug*") -> 3
A11: Types: Bug = something is wrong now; Missing feature = not built; Enhancement = built but weak; Design gap = built in a way that cannot work; Gap = a missing piece. Size: S under 1 day, M about 1 to 2 days, L more. Update the Status column to Fixed only when the story is Done.
A12: Gap ID | B12: No. in your list | C12: Area | D12: Type | E12: What is wrong or missing | F12: What the code shows (root cause or current state) | G12: Recommended fix and the better way | H12: Priority | I12: Size | J12: Depends on | K12: Sprint 6 story | L12: Status
A13: G-01 | B13: 1 | C13: Organization | D13: Missing feature | E13: The Department page has no detail view: who is in a department, what each person does, what work is running. | F13: Departments have only list and create/edit/delete. Department has no head field and there is no overview endpoint. Task visibility follows the hierarchy rule (FR-13), so a detail page must not show everyone's tasks to everyone. | G13: Department detail page with a GET /departments/{id}/overview/ endpoint: members with designation, manager and open-task counts, a task summary and the running tasks. Add Department.head. Task titles only to people who may see them; everybody else sees counts. | H13: High | I13: L | J13: G-04 | K13: ST-150 | L13: Open
A14: G-02 | B14: 2 | C14: Organization | D14: Enhancement | E14: The Designations page is only a list; it needs improving and probably a detail page. | F14: List and CRUD only. Deleting a Designation silently clears the link on every employee who holds it (the foreign key is SET_NULL). | G14: Designation detail page listing the people who hold it, with department. Refuse the delete while the Designation is in use and say who holds it. | H14: Medium | I14: S | J14: G-04 | K14: ST-150 | L14: Open
A15: G-03 | B15: 3 | C15: Organization | D15: Bug | E15: On the Employee page, creating an employee shows email and password already filled in by the browser. | F15: The form inputs have no autocomplete attributes, so the browser password manager fills in the logged-in user's own saved login. | G15: Set autocomplete off and new-password. Better way: the CEO never types an employee's password; the system makes a one-time temporary password shown once, and the employee must change it at first login. | H15: Medium | I15: S | J15: G-09 | K15: ST-142 | L15: Open
A16: G-04 | B16: 4 | C16: Profile | D16: Missing feature | E16: The Employee detail page is weak: it needs name and email, a full profile, and a permission-wise view of what the person can do. | F16: No name exists anywhere: User has only an email and Employee only an employee code. The page shows hierarchy only. The Roles a person holds are not expanded into Permissions. | G16: Add full_name (User) and profile fields (Employee: phone, address, emergency contact, joined on). Detail page with the profile, hierarchy and the effective Permissions per Role. Contact data only for the person, their managers and manage_employees; salary only with manage_finance. | H16: High | I16: L | J16: G-05 | K16: ST-140, ST-143 | L16: Open
A17: G-05 | B17: 5 | C17: RBAC | D17: Enhancement | E17: The Roles page offers only a few Permission checkboxes; they should be many and arranged in sections. | F17: The catalog really has 14 Permissions. The page hardcodes 12 names and 6 of them do not exist in the backend. Permissions have no module sections on screen. | G17: Permission catalog in code (codename, name, module, description) synced on migrate; a sectioned picker with Select all. Add a new Permission only together with the feature it protects, because a Permission that protects nothing is misleading. | H17: High | I17: M | J17: G-08 | K17: ST-138, ST-139 | L17: Open
A18: G-06 | B18: 6 | C18: RBAC | D18: Missing feature | E18: There is no page that explains what each Permission and each Role lets a person do; headings alone are not clear. | F18: The Permission API returns only codename, name and module. There is no description and no Role detail page. | G18: A plain-language description for every Permission and a Role detail page that groups Permissions by module with those descriptions and lists the people who hold the Role. | H18: High | I18: M | J18: G-05 | K18: ST-138, ST-139 | L18: Open
A19: G-07 | B19: 7 | C19: RBAC | D19: Missing feature | E19: A Role cannot be edited after it is created. | F19: The API already allows PUT and PATCH with manage_roles; the page has only create and delete. The CEO system Role must stay locked. | G19: Edit form for name, description and Permissions, with a warning of how many employees are affected; the CEO Role stays read-only and says why. | H19: High | I19: S | J19: G-05 | K19: ST-139 | L19: Open
A20: G-08 | B20: 8 | C20: RBAC | D20: Bug | E20: A Role created with many Permissions shows only 4 in the existing-Roles list. | F20: Root cause found in the code: six of the page's hardcoded names (approve_leave, approve_request, manage_attendance, manage_payroll, view_finance, approve_expense) do not exist in the backend; the create handler keeps only real ids and silently drops the rest, so the Role is saved with fewer Permissions and the page never says so. | G20: Use the backend catalog as the only source for the page; if a ticked Permission is not saved, show an error; add a test that every permission_required codename used in the views exists in the catalog so this class of bug cannot return. | H20: High | I20: S | J20: — | K20: ST-138 | L20: Open
A21: G-09 | B21: 9 | C21: Profile | D21: Missing feature | E21: Every employee should have their own profile section where they can see and edit their details. | F21: /auth/me/ is read-only. There is no self-edit endpoint and no change-password endpoint. | G21: GET and PATCH /auth/profile/ with a whitelist (full name, phone, address, emergency contact); email, department, designation, manager, Roles and salary can never be changed through it. Change password needs the current password and ends other sessions. A My Profile page. | H21: High | I21: M | J21: G-04 | K21: ST-140, ST-141, ST-142 | L21: Open
A22: G-10 | B22: 10 | C22: Attendance | D22: Missing feature | E22: A CEO or anyone with the Permission should see all employees' attendance (days present, times) by choosing an employee from a dropdown. | F22: The attendance API is own-data only. The SRS marks FR-13 as Partly for exactly this: a manager cannot list a team member's attendance. | G22: A new Permission view_team_attendance; a team endpoint built on the existing month calendar plus check-in, check-out and hours; scope is the whole company with the Permission, otherwise the user's subordinates; outside scope answers 404. | H22: High | I22: M | J22: G-05 | K22: ST-144 | L22: Open
A23: G-11 | B23: 11 | C23: Profile | D23: Missing feature | E23: The Platform Admin side needs a profile section too. | F23: A Platform Admin is a User without an Employee, with no name and no profile page. | G23: Reuse the same profile endpoint and My Profile page (full_name lives on User, so it works without an Employee). | H23: Low | I23: S | J23: G-09 | K23: ST-140, ST-141 | L23: Open
A24: G-12 | B24: 12 | C24: Platform Admin | D24: Missing feature | E24: The Companies page has no company detail page; the Platform Admin needs a company's details and its CEO's information. | F24: The page is a list with Suspend and Activate only; there is no detail endpoint. | G24: Company detail page and endpoint: plan, subscription timeline, owner (CEO) contact, employee count against the limit, payments and tickets summary, recent platform actions. Counts and contacts only, never employee names, tasks or salary, so Break-Glass stays the only way into company data. | H24: Medium | I24: M | J24: G-17 | K24: ST-152 | L24: Open
... A35: G-23 | B35: 23 | C35: UI | D35: Cleanup | E35: Sidebar items marked Soon must be completed or removed. | F35: Projects, Payroll and Expenses are muted Soon items. Payroll is already covered by Salary Structures and Payslips; Projects and Expense are listed as Not built in the SRS. | G35: Remove all three so nothing in the menu looks unfinished. | H35: Low | I35: S | J35: — | K35: ST-154 | L35: Open
A36: X-01 | B36: — | C36: RBAC | D36: Gap (found in analysis) | E36: Deleting a Role that employees still hold is not handled. | F36: The error-handling reference lists it as Not handled; only the CEO system Role and a Role used by an approval step are protected. | G36: Refuse the delete with code ROLE_IN_USE and show who holds the Role. | H36: Medium | I36: S | J36: G-07 | K36: ST-139 | L36: Open
A37: X-02 | B37: — | C37: Organization | D37: Bug (found in analysis) | E37: Deleting a Department silently clears the Department on its employees. | F37: Employee.department is SET_NULL. | G37: Refuse the delete while the Department has employees and say who is in it (same rule as the Designation). | H37: Medium | I37: S | J37: G-01 | K37: ST-150 | L37: Open
A38: X-03 | B38: — | C38: Billing | D38: Design gap (found in analysis) | E38: A company that is deactivated for non-payment could not even log in to pay. | F38: Suspend (is_active false) blocks login and every request, which is right for a misuse suspension but wrong for an unpaid plan. | G38: A separate restricted mode: the user logs in, but only Billing, payment, profile and support endpoints work (code SUBSCRIPTION_RESTRICTED). The same gate also holds a new company in pending_payment, so one mechanism serves both. Suspend stays a full block. | H38: High | I38: M | J38: G-17, G-18 | K38: ST-145 | L38: Open
A39: X-04 | B39: — | C39: RBAC | D39: Gap (found in analysis) | E39: Nothing checks that the codenames used in the views exist in the Permission catalog, which is how G-08 happened. | F39: Permission codenames are plain strings in views and in the frontend. | G39: A test that reads every permission_required in the ViewSets and fails if the codename is not in the catalog. | H39: High | I39: S | J39: G-08 | K39: ST-138 | L39: Open
A40: X-05 | B40: — | C40: Profile | D40: Gap (found in analysis) | E40: Users cannot change their password and cannot end their other sessions. | F40: There is no change-password endpoint. | G40: Change password with the current password; blacklist the user's other refresh tokens; a temporary password forces a change at first login. | H40: High | I40: M | J40: G-09 | K40: ST-142 | L40: Open
A41: X-06 | B41: — | C41: Billing | D41: Design rule (found in analysis) | E41: Manual payments can be faked or repeated. | F41: No payment model exists yet. | G41: The amount is always computed on the server, a transaction id is unique per method, one pending submission per company, and the approval is idempotent (locked row) so approving twice never extends twice. A company can never approve its own payment. | H41: High | I41: M | J41: G-18 | K41: ST-146 | L41: Open
A42: X-07 | B42: — | C42: Quality | D42: Gap (found in analysis) | E42: The SRS traceability list and the documents do not yet know the new features. | F42: Documents are generated from the code, but the requirement list is a hand-kept table with code evidence. | G42: Add the new requirements with evidence, regenerate the documents, update the demo script. | H42: Medium | I42: S | J42: all | K42: ST-155 | L42: Open
A43: X-08 | B43: — | C43: Quality | D43: Risk (found in analysis) | E43: Existing tests and Selenium helpers assume a company is active right after register and that an employee is created with a typed password. | F43: register_company in the backend test helpers and the Selenium login flow. | G43: Keep an explicit-password path for employee creation; make the register_company test helper activate the subscription; update the Selenium helpers in ST-154. | H43: Medium | I43: S | J43: G-18 | K43: ST-145, ST-155 | L43: Open
